<?xml version="1.0" encoding="utf-8"?>
<Return xmlns="http://www.irs.gov/efile" xmlns:xsi="http://www.w3.org/2001/XMLSchema-instance" returnVersion="2015v2.0" xsi:schemaLocation="http://www.irs.gov/efile">
  <ReturnHeader binaryAttachmentCnt="0">
    <ReturnTs>2016-08-15T10:40:26-07:00</ReturnTs>
    <TaxPeriodEndDt>2015-12-31</TaxPeriodEndDt>
    <PreparerFirmGrp>
      <PreparerFirmName>
        <BusinessNameLine1Txt>Eric J Sterling CPA AAC</BusinessNameLine1Txt>
      </PreparerFirmName>
      <PreparerUSAddress>
        <AddressLine1Txt>26500 W Agoura Road Ste 211</AddressLine1Txt>
        <CityNm>Calabasas</CityNm>
        <StateAbbreviationCd>CA</StateAbbreviationCd>
        <ZIPCd>91302</ZIPCd>
      </PreparerUSAddress>
    </PreparerFirmGrp>
    <ReturnTypeCd>990PF</ReturnTypeCd>
    <TaxPeriodBeginDt>2015-01-01</TaxPeriodBeginDt>
    <Filer>
      <EIN>205502440</EIN>
      <BusinessName>
        <BusinessNameLine1Txt>THE L &amp; A SHAPIRO FAMILY FOUNDATION</BusinessNameLine1Txt>
      </BusinessName>
      <BusinessNameControlTxt>L&amp;AS</BusinessNameControlTxt>
      <PhoneNum>3102641666</PhoneNum>
      <USAddress>
        <AddressLine1Txt>1666 20TH STREET</AddressLine1Txt>
        <CityNm>SANTA MONICA</CityNm>
        <StateAbbreviationCd>CA</StateAbbreviationCd>
        <ZIPCd>90404</ZIPCd>
      </USAddress>
    </Filer>
    <BusinessOfficerGrp>
      <PersonNm>LEONARD SHAPIRO</PersonNm>
      <PersonTitleTxt>President</PersonTitleTxt>
      <SignatureDt>2016-08-02</SignatureDt>
      <DiscussWithPaidPreparerInd>true</DiscussWithPaidPreparerInd>
    </BusinessOfficerGrp>
    <PreparerPersonGrp>
      <PreparerPersonNm>ERIC J STERLING</PreparerPersonNm>
      <PTIN>P00110413</PTIN>
      <PhoneNum>8187469214</PhoneNum>
    </PreparerPersonGrp>
    <TaxYr>2015</TaxYr>
    <BuildTS>2016-12-15 16:53:06Z</BuildTS>
  </ReturnHeader>
  <ReturnData documentCnt="4">
    <IRS990PF documentId="IRS990PF" referenceDocumentId="GeneralExplanation" softwareId="15000324" softwareVersionNum="2015v2.0">
      <Organization501c3ExemptPFInd>X</Organization501c3ExemptPFInd>
      <FMVAssetsEOYAmt>449975</FMVAssetsEOYAmt>
      <MethodOfAccountingCashInd>X</MethodOfAccountingCashInd>
      <AnalysisOfRevenueAndExpenses>
        <ScheduleBNotRequiredInd>X</ScheduleBNotRequiredInd>
        <TotalRevAndExpnssAmt>0</TotalRevAndExpnssAmt>
        <TotalNetInvstIncmAmt>0</TotalNetInvstIncmAmt>
        <TaxesRevAndExpnssAmt referenceDocumentId="TaxesSchedule">42</TaxesRevAndExpnssAmt>
        <TaxesNetInvstIncmAmt>42</TaxesNetInvstIncmAmt>
        <TaxesAdjNetIncmAmt>42</TaxesAdjNetIncmAmt>
        <OtherExpensesRevAndExpnssAmt referenceDocumentId="OtherExpensesSchedule AmortizationSchedule">466</OtherExpensesRevAndExpnssAmt>
        <OtherExpensesNetInvstIncmAmt>466</OtherExpensesNetInvstIncmAmt>
        <OtherExpensesAdjNetIncmAmt>466</OtherExpensesAdjNetIncmAmt>
        <OtherExpensesDsbrsChrtblAmt>466</OtherExpensesDsbrsChrtblAmt>
        <TotOprExpensesRevAndExpnssAmt>508</TotOprExpensesRevAndExpnssAmt>
        <TotOprExpensesNetInvstIncmAmt>508</TotOprExpensesNetInvstIncmAmt>
        <TotOprExpensesAdjNetIncmAmt>508</TotOprExpensesAdjNetIncmAmt>
        <TotOprExpensesDsbrsChrtblAmt>466</TotOprExpensesDsbrsChrtblAmt>
        <ContriPaidRevAndExpnssAmt>0</ContriPaidRevAndExpnssAmt>
        <ContriPaidDsbrsChrtblAmt>0</ContriPaidDsbrsChrtblAmt>
        <TotalExpensesRevAndExpnssAmt>508</TotalExpensesRevAndExpnssAmt>
        <TotalExpensesNetInvstIncmAmt>508</TotalExpensesNetInvstIncmAmt>
        <TotalExpensesAdjNetIncmAmt>508</TotalExpensesAdjNetIncmAmt>
        <TotalExpensesDsbrsChrtblAmt>466</TotalExpensesDsbrsChrtblAmt>
        <ExcessRevenueOverExpensesAmt>-508</ExcessRevenueOverExpensesAmt>
        <NetInvestmentIncomeAmt>0</NetInvestmentIncomeAmt>
      </AnalysisOfRevenueAndExpenses>
      <Form990PFBalanceSheetsGrp>
        <CashBOYAmt>242198</CashBOYAmt>
        <CashEOYAmt>141690</CashEOYAmt>
        <CashEOYFMVAmt>251407</CashEOYFMVAmt>
        <SavAndTempCashInvstBOYAmt>109718</SavAndTempCashInvstBOYAmt>
        <SavAndTempCashInvstEOYAmt>109718</SavAndTempCashInvstEOYAmt>
        <SavAndTempCashInvstEOYFMVAmt>109718</SavAndTempCashInvstEOYFMVAmt>
        <CorporateBondsEOYAmt referenceDocumentId="InvestmentsCorpBondsSchedule">100000</CorporateBondsEOYAmt>
        <CorporateBondsEOYFMVAmt>88850</CorporateBondsEOYFMVAmt>
        <TotalAssetsBOYAmt>351916</TotalAssetsBOYAmt>
        <TotalAssetsEOYAmt>351408</TotalAssetsEOYAmt>
        <TotalAssetsEOYFMVAmt>449975</TotalAssetsEOYFMVAmt>
        <TotalLiabilitiesEOYAmt>0</TotalLiabilitiesEOYAmt>
        <OrgDoesNotFollowSFAS117Ind>X</OrgDoesNotFollowSFAS117Ind>
        <CapitalStockBOYAmt>351916</CapitalStockBOYAmt>
        <CapitalStockEOYAmt>351408</CapitalStockEOYAmt>
        <TotNetAstOrFundBalancesBOYAmt>351916</TotNetAstOrFundBalancesBOYAmt>
        <TotNetAstOrFundBalancesEOYAmt>351408</TotNetAstOrFundBalancesEOYAmt>
        <TotalLiabilitiesNetAstBOYAmt>351916</TotalLiabilitiesNetAstBOYAmt>
        <TotalLiabilitiesNetAstEOYAmt>351408</TotalLiabilitiesNetAstEOYAmt>
      </Form990PFBalanceSheetsGrp>
      <ChgInNetAssetsFundBalancesGrp>
        <TotNetAstOrFundBalancesBOYAmt>351916</TotNetAstOrFundBalancesBOYAmt>
        <ExcessRevenueOverExpensesAmt>-508</ExcessRevenueOverExpensesAmt>
        <SubtotalAmt>351408</SubtotalAmt>
        <TotNetAstOrFundBalancesEOYAmt>351408</TotNetAstOrFundBalancesEOYAmt>
      </ChgInNetAssetsFundBalancesGrp>
      <ExciseTaxBasedOnInvstIncmGrp>
        <InvestmentIncomeExciseTaxAmt>0</InvestmentIncomeExciseTaxAmt>
      </ExciseTaxBasedOnInvstIncmGrp>
      <StatementsRegardingActyGrp>
        <LegislativePoliticalActyInd>false</LegislativePoliticalActyInd>
        <MoreThan100SpentInd>false</MoreThan100SpentInd>
        <Form1120POLFiledInd>false</Form1120POLFiledInd>
        <ActivitiesNotPreviouslyRptInd>false</ActivitiesNotPreviouslyRptInd>
        <ChangesToArticlesOrBylawsInd>false</ChangesToArticlesOrBylawsInd>
        <UnrelatedBusIncmOverLimitInd>false</UnrelatedBusIncmOverLimitInd>
        <Form990TFiledInd>false</Form990TFiledInd>
        <OrganizationDissolvedEtcInd>false</OrganizationDissolvedEtcInd>
        <Section508eRqrSatisfiedInd>true</Section508eRqrSatisfiedInd>
        <AtLeast5000InAssetsInd>true</AtLeast5000InAssetsInd>
        <OrgReportOrRegisterStateCd>CA</OrgReportOrRegisterStateCd>
        <Form990PFFiledWithAttyGenInd>true</Form990PFFiledWithAttyGenInd>
        <PrivateOperatingFoundationInd>false</PrivateOperatingFoundationInd>
        <NewSubstantialContributorsInd>false</NewSubstantialContributorsInd>
        <OwnControlledEntityInd>false</OwnControlledEntityInd>
        <DonorAdvisedFundInd>false</DonorAdvisedFundInd>
        <ComplyWithPublicInspRqrInd>true</ComplyWithPublicInspRqrInd>
        <WebsiteAddressTxt>N/A</WebsiteAddressTxt>
        <PersonsWithBooksName>
          <BusinessNameLine1Txt>LEONARD SHAPIRO</BusinessNameLine1Txt>
        </PersonsWithBooksName>
        <PhoneNum>3102641666</PhoneNum>
        <LocationOfBooksUSAddress>
          <AddressLine1Txt>1666 20TH STREET SUITE 100</AddressLine1Txt>
          <CityNm>SANTA MONICA</CityNm>
          <StateAbbreviationCd>CA</StateAbbreviationCd>
          <ZIPCd>90404</ZIPCd>
        </LocationOfBooksUSAddress>
        <ForeignAccountsQuestionInd>false</ForeignAccountsQuestionInd>
      </StatementsRegardingActyGrp>
      <StatementsRegardingActy4720Grp>
        <SaleOrExchDisqualifiedPrsnInd>false</SaleOrExchDisqualifiedPrsnInd>
        <BrrwOrLendDisqualifiedPrsnInd>false</BrrwOrLendDisqualifiedPrsnInd>
        <FurnGoodsDisqualifiedPrsnInd>false</FurnGoodsDisqualifiedPrsnInd>
        <PayCompDisqualifiedPrsnInd>false</PayCompDisqualifiedPrsnInd>
        <TransferAstDisqualifiedPrsnInd>false</TransferAstDisqualifiedPrsnInd>
        <PaymentToGovernmentOfficialInd>false</PaymentToGovernmentOfficialInd>
        <ActsFailToQlfyAsExceptionsInd>false</ActsFailToQlfyAsExceptionsInd>
        <UncorrectedPriorActsInd>false</UncorrectedPriorActsInd>
        <UndistributedIncomePYInd>false</UndistributedIncomePYInd>
        <UndistrIncmSect4942a2NotAppInd>false</UndistrIncmSect4942a2NotAppInd>
        <BusinessHoldingsInd>false</BusinessHoldingsInd>
        <ExcessBusinessHoldingsInd>false</ExcessBusinessHoldingsInd>
        <JeopardyInvestmentsInd>false</JeopardyInvestmentsInd>
        <UncorrectedPYJeopardyInvstInd>false</UncorrectedPYJeopardyInvstInd>
        <InfluenceLegislationInd>false</InfluenceLegislationInd>
        <InfluenceElectionInd>false</InfluenceElectionInd>
        <GrantsToIndividualsInd>false</GrantsToIndividualsInd>
        <GrantsToOrganizationsInd>false</GrantsToOrganizationsInd>
        <NoncharitablePurposeInd>false</NoncharitablePurposeInd>
        <TransactionsFailToQlfyAsExcInd>false</TransactionsFailToQlfyAsExcInd>
        <MaintainedExpenditureRspnsInd>false</MaintainedExpenditureRspnsInd>
        <RcvFndsToPayPrsnlBnftCntrctInd>false</RcvFndsToPayPrsnlBnftCntrctInd>
        <PayPremiumsPrsnlBnftCntrctInd>false</PayPremiumsPrsnlBnftCntrctInd>
        <ProhibitedTaxShelterTransInd>false</ProhibitedTaxShelterTransInd>
        <ProceedsOrNetIncomeInd>false</ProceedsOrNetIncomeInd>
      </StatementsRegardingActy4720Grp>
      <OfficerDirTrstKeyEmplInfoGrp>
        <OfficerDirTrstKeyEmplGrp>
          <PersonNm>LEONARD SHAPIRO</PersonNm>
          <USAddress>
            <AddressLine1Txt>1666 20TH STREET SUITE 100</AddressLine1Txt>
            <CityNm>SANTA MONICA</CityNm>
            <StateAbbreviationCd>CA</StateAbbreviationCd>
            <ZIPCd>90404</ZIPCd>
          </USAddress>
          <TitleTxt>President</TitleTxt>
          <AverageHrsPerWkDevotedToPosRt>0.00</AverageHrsPerWkDevotedToPosRt>
          <CompensationAmt>0</CompensationAmt>
        </OfficerDirTrstKeyEmplGrp>
        <OfficerDirTrstKeyEmplGrp>
          <PersonNm>ANNETTE SHAPIRO</PersonNm>
          <USAddress>
            <AddressLine1Txt>1666 20TH STREET SUITE 100</AddressLine1Txt>
            <CityNm>SANTA MONICA</CityNm>
            <StateAbbreviationCd>CA</StateAbbreviationCd>
            <ZIPCd>90404</ZIPCd>
          </USAddress>
          <TitleTxt>Secretary</TitleTxt>
          <AverageHrsPerWkDevotedToPosRt>0.00</AverageHrsPerWkDevotedToPosRt>
          <CompensationAmt>0</CompensationAmt>
        </OfficerDirTrstKeyEmplGrp>
        <CompOfHghstPdEmplOrNONETxt>NONE</CompOfHghstPdEmplOrNONETxt>
        <CompOfHghstPdCntrctOrNONETxt>NONE</CompOfHghstPdCntrctOrNONETxt>
      </OfficerDirTrstKeyEmplInfoGrp>
      <MinimumInvestmentReturnGrp>
        <AverageMonthlyFMVOfSecAmt>0</AverageMonthlyFMVOfSecAmt>
        <AverageMonthlyCashBalancesAmt>0</AverageMonthlyCashBalancesAmt>
        <FMVAllOtherNoncharitableAstAmt>0</FMVAllOtherNoncharitableAstAmt>
        <TotalFMVOfUnusedAssetsAmt>0</TotalFMVOfUnusedAssetsAmt>
        <ReductionClaimedAmt>0</ReductionClaimedAmt>
        <AdjustedTotalFMVOfUnusedAstAmt>0</AdjustedTotalFMVOfUnusedAstAmt>
        <CashDeemedCharitableAmt>0</CashDeemedCharitableAmt>
        <NetVlNoncharitableAssetsAmt>0</NetVlNoncharitableAssetsAmt>
        <MinimumInvestmentReturnAmt>0</MinimumInvestmentReturnAmt>
      </MinimumInvestmentReturnGrp>
      <DistributableAmountGrp>
        <DistributableAsAdjustedAmt>0</DistributableAsAdjustedAmt>
      </DistributableAmountGrp>
      <QualifyingDistriPartXIIGrp>
        <ExpensesAndContributionsAmt>466</ExpensesAndContributionsAmt>
        <QualifyingDistributionsAmt>466</QualifyingDistributionsAmt>
        <AdjustedQualifyingDistriAmt>466</AdjustedQualifyingDistriAmt>
      </QualifyingDistriPartXIIGrp>
      <UndistributedIncomeGrp>
        <DistributableAsAdjustedAmt>0</DistributableAsAdjustedAmt>
        <ExcessDistributionCyovYr3Amt>8578</ExcessDistributionCyovYr3Amt>
        <ExcessDistributionCyovYr1Amt>12100</ExcessDistributionCyovYr1Amt>
        <TotalExcessDistributionCyovAmt>20678</TotalExcessDistributionCyovAmt>
        <QualifyingDistributionsAmt>466</QualifyingDistributionsAmt>
        <TreatedAsDistriFromCorpusAmt>0</TreatedAsDistriFromCorpusAmt>
        <RemainingDistriFromCorpusAmt>466</RemainingDistriFromCorpusAmt>
        <TotalCorpusAmt>21144</TotalCorpusAmt>
        <UndistributedIncomeCYAmt>0</UndistributedIncomeCYAmt>
        <ExcessDistriCyovToNextYrAmt>21144</ExcessDistriCyovToNextYrAmt>
        <ExcessFromYear3Amt>8578</ExcessFromYear3Amt>
        <ExcessFromYear1Amt>12100</ExcessFromYear1Amt>
        <ExcessFromCurrentYearAmt>466</ExcessFromCurrentYearAmt>
      </UndistributedIncomeGrp>
      <SupplementaryInformationGrp>
        <OnlyContriToPreselectedInd>X</OnlyContriToPreselectedInd>
      </SupplementaryInformationGrp>
      <TrnsfrTransRlnNonchrtblEOGrp>
        <TrnsfrOfCashToNonchrtblEOInd>false</TrnsfrOfCashToNonchrtblEOInd>
        <TrnsfrOtherAssetNonchrtblEOInd>false</TrnsfrOtherAssetNonchrtblEOInd>
        <SalesOrExchangesOfAssetsInd>false</SalesOrExchangesOfAssetsInd>
        <PurchaseOfAssetsNonchrtblEOInd>false</PurchaseOfAssetsNonchrtblEOInd>
        <RentalOfFacilitiesOthAssetsInd>false</RentalOfFacilitiesOthAssetsInd>
        <ReimbursementArrangementsInd>false</ReimbursementArrangementsInd>
        <LoansOrLoanGuaranteesInd>false</LoansOrLoanGuaranteesInd>
        <PerformanceOfServicesEtcInd>false</PerformanceOfServicesEtcInd>
        <SharingOfFacilitiesEtcInd>false</SharingOfFacilitiesEtcInd>
        <RelationshipsNonchrtblEOInd>false</RelationshipsNonchrtblEOInd>
      </TrnsfrTransRlnNonchrtblEOGrp>
    </IRS990PF>
    <InvestmentsCorpBondsSchedule documentId="InvestmentsCorpBondsSchedule" softwareId="15000324" softwareVersionNum="2015v2.0">
      <InvestmentsCorporateBondsGrp>
        <BondNm>100000 SOCIETEGENERALE REV CONV NT LKD</BondNm>
        <EOYBookValueAmt>100000</EOYBookValueAmt>
        <EOYFMVAmt>88850</EOYFMVAmt>
      </InvestmentsCorporateBondsGrp>
    </InvestmentsCorpBondsSchedule>
    <OtherExpensesSchedule documentId="OtherExpensesSchedule" softwareId="15000324" softwareVersionNum="2015v2.0">
      <OtherExpensesScheduleGrp>
        <Desc>OFFICE</Desc>
        <RevenueAndExpensesPerBooksAmt>466</RevenueAndExpensesPerBooksAmt>
        <NetInvestmentIncomeAmt>466</NetInvestmentIncomeAmt>
        <AdjustedNetIncomeAmt>466</AdjustedNetIncomeAmt>
        <DisbursementsCharitablePrpsAmt>466</DisbursementsCharitablePrpsAmt>
      </OtherExpensesScheduleGrp>
    </OtherExpensesSchedule>
    <TaxesSchedule documentId="TaxesSchedule" softwareId="15000324" softwareVersionNum="2015v2.0">
      <TaxesDetail>
        <CategoryTxt>FRANCHISE TAX BOARD</CategoryTxt>
        <Amt>42</Amt>
        <NetInvestmentIncomeAmt>42</NetInvestmentIncomeAmt>
        <AdjustedNetIncomeAmt>42</AdjustedNetIncomeAmt>
      </TaxesDetail>
    </TaxesSchedule>
  </ReturnData>
</Return>