<?xml version="1.0" encoding="utf-8"?>
<Return xmlns="http://www.irs.gov/efile" xmlns:xsi="http://www.w3.org/2001/XMLSchema-instance" xsi:schemaLocation="http://www.irs.gov/efile" returnVersion="2015v2.1">
  <ReturnHeader binaryAttachmentCnt="0">
    <ReturnTs>2016-09-14T18:40:48-05:00</ReturnTs>
    <TaxPeriodEndDt>2016-06-30</TaxPeriodEndDt>
    <PreparerFirmGrp>
      <PreparerFirmEIN>770546629</PreparerFirmEIN>
      <PreparerFirmName>
        <BusinessNameLine1Txt>ISABEL CHIU &amp; CO LLP</BusinessNameLine1Txt>
      </PreparerFirmName>
      <PreparerUSAddress>
        <AddressLine1Txt>838 N HILLVIEW DRIVE</AddressLine1Txt>
        <CityNm>MILPITAS</CityNm>
        <StateAbbreviationCd>CA</StateAbbreviationCd>
        <ZIPCd>95035</ZIPCd>
      </PreparerUSAddress>
    </PreparerFirmGrp>
    <ReturnTypeCd>990PF</ReturnTypeCd>
    <TaxPeriodBeginDt>2015-07-01</TaxPeriodBeginDt>
    <Filer>
      <EIN>461461715</EIN>
      <BusinessName>
        <BusinessNameLine1Txt>FMCK LEE FOUNDATION</BusinessNameLine1Txt>
      </BusinessName>
      <BusinessNameControlTxt>FMCK</BusinessNameControlTxt>
      <PhoneNum>4083957837</PhoneNum>
      <USAddress>
        <AddressLine1Txt>15997 GRANDVIEW AVENUE</AddressLine1Txt>
        <CityNm>MONTE SERENO</CityNm>
        <StateAbbreviationCd>CA</StateAbbreviationCd>
        <ZIPCd>95030</ZIPCd>
      </USAddress>
    </Filer>
    <BusinessOfficerGrp>
      <PersonNm>FRANK LEE</PersonNm>
      <PersonTitleTxt>PRESIDENT</PersonTitleTxt>
      <PhoneNum>4083957837</PhoneNum>
      <SignatureDt>2016-08-09</SignatureDt>
      <DiscussWithPaidPreparerInd>1</DiscussWithPaidPreparerInd>
    </BusinessOfficerGrp>
    <PreparerPersonGrp>
      <PreparerPersonNm>ISABEL CHIU CPA</PreparerPersonNm>
      <PTIN>P00185602</PTIN>
      <PhoneNum>4089429689</PhoneNum>
    </PreparerPersonGrp>
    <TaxYr>2015</TaxYr>
    <BuildTS>2017-02-10 21:41:12Z</BuildTS>
  </ReturnHeader>
  <ReturnData documentCnt="5">
    <IRS990PF documentId="RetDoc1235000001">
      <Organization501c3ExemptPFInd>X</Organization501c3ExemptPFInd>
      <FMVAssetsEOYAmt>17877</FMVAssetsEOYAmt>
      <MethodOfAccountingCashInd>X</MethodOfAccountingCashInd>
      <AnalysisOfRevenueAndExpenses>
        <ContriRcvdRevAndExpnssAmt>0</ContriRcvdRevAndExpnssAmt>
        <ScheduleBNotRequiredInd>X</ScheduleBNotRequiredInd>
        <DividendsRevAndExpnssAmt>440</DividendsRevAndExpnssAmt>
        <DividendsNetInvstIncmAmt>440</DividendsNetInvstIncmAmt>
        <NetGainSaleAstRevAndExpnssAmt>1368</NetGainSaleAstRevAndExpnssAmt>
        <GrossSalesPriceAmt>9624</GrossSalesPriceAmt>
        <CapGainNetIncmNetInvstIncmAmt>1368</CapGainNetIncmNetInvstIncmAmt>
        <TotalRevAndExpnssAmt>1808</TotalRevAndExpnssAmt>
        <TotalNetInvstIncmAmt>1808</TotalNetInvstIncmAmt>
        <CompOfcrDirTrstRevAndExpnssAmt>0</CompOfcrDirTrstRevAndExpnssAmt>
        <CompOfcrDirTrstNetInvstIncmAmt>0</CompOfcrDirTrstNetInvstIncmAmt>
        <CompOfcrDirTrstDsbrsChrtblAmt>0</CompOfcrDirTrstDsbrsChrtblAmt>
        <AccountingFeesRevAndExpnssAmt referenceDocumentId="RetDoc2002200001">2850</AccountingFeesRevAndExpnssAmt>
        <AccountingFeesNetInvstIncmAmt>2100</AccountingFeesNetInvstIncmAmt>
        <AccountingFeesChrtblPrpsAmt>750</AccountingFeesChrtblPrpsAmt>
        <TaxesRevAndExpnssAmt referenceDocumentId="RetDoc2002500001">152</TaxesRevAndExpnssAmt>
        <TaxesNetInvstIncmAmt>152</TaxesNetInvstIncmAmt>
        <TaxesDsbrsChrtblAmt>0</TaxesDsbrsChrtblAmt>
        <OtherExpensesRevAndExpnssAmt referenceDocumentId="RetDoc2003200001">450</OtherExpensesRevAndExpnssAmt>
        <OtherExpensesNetInvstIncmAmt>450</OtherExpensesNetInvstIncmAmt>
        <OtherExpensesDsbrsChrtblAmt>0</OtherExpensesDsbrsChrtblAmt>
        <TotOprExpensesRevAndExpnssAmt>3452</TotOprExpensesRevAndExpnssAmt>
        <TotOprExpensesNetInvstIncmAmt>2702</TotOprExpensesNetInvstIncmAmt>
        <TotOprExpensesDsbrsChrtblAmt>750</TotOprExpensesDsbrsChrtblAmt>
        <ContriPaidRevAndExpnssAmt>0</ContriPaidRevAndExpnssAmt>
        <ContriPaidDsbrsChrtblAmt>0</ContriPaidDsbrsChrtblAmt>
        <TotalExpensesRevAndExpnssAmt>3452</TotalExpensesRevAndExpnssAmt>
        <TotalExpensesNetInvstIncmAmt>2702</TotalExpensesNetInvstIncmAmt>
        <TotalExpensesDsbrsChrtblAmt>750</TotalExpensesDsbrsChrtblAmt>
        <ExcessRevenueOverExpensesAmt>-1644</ExcessRevenueOverExpensesAmt>
        <NetInvestmentIncomeAmt>0</NetInvestmentIncomeAmt>
      </AnalysisOfRevenueAndExpenses>
      <Form990PFBalanceSheetsGrp>
        <SavAndTempCashInvstBOYAmt>714</SavAndTempCashInvstBOYAmt>
        <SavAndTempCashInvstEOYAmt>7327</SavAndTempCashInvstEOYAmt>
        <SavAndTempCashInvstEOYFMVAmt>7327</SavAndTempCashInvstEOYFMVAmt>
        <CorporateStockBOYAmt>8306</CorporateStockBOYAmt>
        <CorporateStockEOYAmt referenceDocumentId="RetDoc2018900001">49</CorporateStockEOYAmt>
        <CorporateStockEOYFMVAmt>10550</CorporateStockEOYFMVAmt>
        <TotalAssetsBOYAmt>9020</TotalAssetsBOYAmt>
        <TotalAssetsEOYAmt>7376</TotalAssetsEOYAmt>
        <TotalAssetsEOYFMVAmt>17877</TotalAssetsEOYFMVAmt>
        <TotalLiabilitiesBOYAmt>0</TotalLiabilitiesBOYAmt>
        <TotalLiabilitiesEOYAmt>0</TotalLiabilitiesEOYAmt>
        <OrganizationFollowsSFAS117Ind>X</OrganizationFollowsSFAS117Ind>
        <UnrestrictedBOYAmt>9020</UnrestrictedBOYAmt>
        <UnrestrictedEOYAmt>7376</UnrestrictedEOYAmt>
        <TotNetAstOrFundBalancesBOYAmt>9020</TotNetAstOrFundBalancesBOYAmt>
        <TotNetAstOrFundBalancesEOYAmt>7376</TotNetAstOrFundBalancesEOYAmt>
        <TotalLiabilitiesNetAstBOYAmt>9020</TotalLiabilitiesNetAstBOYAmt>
        <TotalLiabilitiesNetAstEOYAmt>7376</TotalLiabilitiesNetAstEOYAmt>
      </Form990PFBalanceSheetsGrp>
      <ChgInNetAssetsFundBalancesGrp>
        <TotNetAstOrFundBalancesBOYAmt>9020</TotNetAstOrFundBalancesBOYAmt>
        <ExcessRevenueOverExpensesAmt>-1644</ExcessRevenueOverExpensesAmt>
        <OtherIncreasesAmt>0</OtherIncreasesAmt>
        <SubtotalAmt>7376</SubtotalAmt>
        <OtherDecreasesAmt>0</OtherDecreasesAmt>
        <TotNetAstOrFundBalancesEOYAmt>7376</TotNetAstOrFundBalancesEOYAmt>
      </ChgInNetAssetsFundBalancesGrp>
      <CapGainsLossTxInvstIncmDetail>
        <CapGainsLossTxInvstIncmGrp>
          <PropertyDesc>352 SH SPWR</PropertyDesc>
          <HowAcquiredCd>P</HowAcquiredCd>
          <AcquiredDt>2013-07-15</AcquiredDt>
          <GrossSalesPriceAmt>9624</GrossSalesPriceAmt>
          <CostOrOtherBasisAmt>8256</CostOrOtherBasisAmt>
          <GainOrLossAmt>1368</GainOrLossAmt>
          <GainsMinusExcessOrLossesAmt>1368</GainsMinusExcessOrLossesAmt>
        </CapGainsLossTxInvstIncmGrp>
        <CapitalGainNetIncomeAmt>1368</CapitalGainNetIncomeAmt>
      </CapGainsLossTxInvstIncmDetail>
      <QlfyUndSect4940eReducedTaxGrp>
        <LiableSection4942TaxInd>0</LiableSection4942TaxInd>
        <AdjustedQlfyDistriYr1Amt>31483</AdjustedQlfyDistriYr1Amt>
        <NetVlNoncharitableAssetsYr1Amt>47525</NetVlNoncharitableAssetsYr1Amt>
        <DistributionYr1Rt>0.662451</DistributionYr1Rt>
        <AdjustedQlfyDistriYr2Amt>19500</AdjustedQlfyDistriYr2Amt>
        <NetVlNoncharitableAssetsYr2Amt>42253</NetVlNoncharitableAssetsYr2Amt>
        <DistributionYr2Rt>0.461506</DistributionYr2Rt>
        <TotalDistributionRt>1.123957</TotalDistributionRt>
        <AverageDistributionRt>0.561979</AverageDistributionRt>
        <NetVlNoncharitableAssetsAmt>18167</NetVlNoncharitableAssetsAmt>
        <AdjNetVlNoncharitableAssetsAmt>10209</AdjNetVlNoncharitableAssetsAmt>
        <NetInvestmentIncomePctAmt>0</NetInvestmentIncomePctAmt>
        <AdjNonchrtblNetInvstIncmPctAmt>10209</AdjNonchrtblNetInvstIncmPctAmt>
        <QualifyingDistributionsAmt>750</QualifyingDistributionsAmt>
      </QlfyUndSect4940eReducedTaxGrp>
      <ExciseTaxBasedOnInvstIncmGrp>
        <InvestmentIncomeExciseTaxAmt>0</InvestmentIncomeExciseTaxAmt>
        <TaxUnderSection511Amt>0</TaxUnderSection511Amt>
        <SubtotalAmt>0</SubtotalAmt>
        <SubtitleATaxAmt>0</SubtitleATaxAmt>
        <TaxBasedOnInvestmentIncomeAmt>0</TaxBasedOnInvestmentIncomeAmt>
        <TotalPaymentsAndCreditsAmt>0</TotalPaymentsAndCreditsAmt>
        <TaxDueAmt>0</TaxDueAmt>
      </ExciseTaxBasedOnInvstIncmGrp>
      <StatementsRegardingActyGrp>
        <LegislativePoliticalActyInd>0</LegislativePoliticalActyInd>
        <MoreThan100SpentInd>0</MoreThan100SpentInd>
        <Form1120POLFiledInd>0</Form1120POLFiledInd>
        <Section4955OrganizationTaxAmt>0</Section4955OrganizationTaxAmt>
        <Section4955ManagersTaxAmt>0</Section4955ManagersTaxAmt>
        <TaxReimbursedAmt>0</TaxReimbursedAmt>
        <ActivitiesNotPreviouslyRptInd>0</ActivitiesNotPreviouslyRptInd>
        <ChangesToArticlesOrBylawsInd>0</ChangesToArticlesOrBylawsInd>
        <UnrelatedBusIncmOverLimitInd>0</UnrelatedBusIncmOverLimitInd>
        <OrganizationDissolvedEtcInd>0</OrganizationDissolvedEtcInd>
        <Section508eRqrSatisfiedInd>0</Section508eRqrSatisfiedInd>
        <AtLeast5000InAssetsInd>1</AtLeast5000InAssetsInd>
        <OrgReportOrRegisterStateCd>CA</OrgReportOrRegisterStateCd>
        <Form990PFFiledWithAttyGenInd>1</Form990PFFiledWithAttyGenInd>
        <PrivateOperatingFoundationInd>0</PrivateOperatingFoundationInd>
        <NewSubstantialContributorsInd>0</NewSubstantialContributorsInd>
        <OwnControlledEntityInd>0</OwnControlledEntityInd>
        <DonorAdvisedFundInd>0</DonorAdvisedFundInd>
        <ComplyWithPublicInspRqrInd>1</ComplyWithPublicInspRqrInd>
        <WebsiteAddressTxt>N/A</WebsiteAddressTxt>
        <IndividualWithBooksNm>ISABEL CHIU CO LLP</IndividualWithBooksNm>
        <PhoneNum>4089429689</PhoneNum>
        <LocationOfBooksUSAddress>
          <AddressLine1Txt>838 NORTH HILLVIEW DRIVE</AddressLine1Txt>
          <CityNm>MILPITAS</CityNm>
          <StateAbbreviationCd>CA</StateAbbreviationCd>
          <ZIPCd>950359776</ZIPCd>
        </LocationOfBooksUSAddress>
        <ForeignAccountsQuestionInd>0</ForeignAccountsQuestionInd>
      </StatementsRegardingActyGrp>
      <StatementsRegardingActy4720Grp>
        <SaleOrExchDisqualifiedPrsnInd>0</SaleOrExchDisqualifiedPrsnInd>
        <BrrwOrLendDisqualifiedPrsnInd>0</BrrwOrLendDisqualifiedPrsnInd>
        <FurnGoodsDisqualifiedPrsnInd>0</FurnGoodsDisqualifiedPrsnInd>
        <PayCompDisqualifiedPrsnInd>0</PayCompDisqualifiedPrsnInd>
        <TransferAstDisqualifiedPrsnInd>0</TransferAstDisqualifiedPrsnInd>
        <PaymentToGovernmentOfficialInd>0</PaymentToGovernmentOfficialInd>
        <UncorrectedPriorActsInd>0</UncorrectedPriorActsInd>
        <UndistributedIncomePYInd>0</UndistributedIncomePYInd>
        <BusinessHoldingsInd>0</BusinessHoldingsInd>
        <JeopardyInvestmentsInd>0</JeopardyInvestmentsInd>
        <UncorrectedPYJeopardyInvstInd>0</UncorrectedPYJeopardyInvstInd>
        <InfluenceLegislationInd>0</InfluenceLegislationInd>
        <InfluenceElectionInd>0</InfluenceElectionInd>
        <GrantsToIndividualsInd>0</GrantsToIndividualsInd>
        <GrantsToOrganizationsInd>0</GrantsToOrganizationsInd>
        <NoncharitablePurposeInd>0</NoncharitablePurposeInd>
        <RcvFndsToPayPrsnlBnftCntrctInd>0</RcvFndsToPayPrsnlBnftCntrctInd>
        <PayPremiumsPrsnlBnftCntrctInd>0</PayPremiumsPrsnlBnftCntrctInd>
        <ProhibitedTaxShelterTransInd>0</ProhibitedTaxShelterTransInd>
      </StatementsRegardingActy4720Grp>
      <OfficerDirTrstKeyEmplInfoGrp>
        <OfficerDirTrstKeyEmplGrp>
          <PersonNm>TSU-WEI FRANK LEE</PersonNm>
          <USAddress>
            <AddressLine1Txt>15997 GRANDVIEW AVENUE</AddressLine1Txt>
            <CityNm>MONTE SERENO</CityNm>
            <StateAbbreviationCd>CA</StateAbbreviationCd>
            <ZIPCd>95030</ZIPCd>
          </USAddress>
          <TitleTxt>PRESIDENT</TitleTxt>
          <AverageHrsPerWkDevotedToPosRt>10.00</AverageHrsPerWkDevotedToPosRt>
          <CompensationAmt>0</CompensationAmt>
          <EmployeeBenefitProgramAmt>0</EmployeeBenefitProgramAmt>
          <ExpenseAccountOtherAllwncAmt>0</ExpenseAccountOtherAllwncAmt>
        </OfficerDirTrstKeyEmplGrp>
        <OfficerDirTrstKeyEmplGrp>
          <PersonNm>KATHERINE LEE</PersonNm>
          <USAddress>
            <AddressLine1Txt>15997 GRANDVIEW AVENUE</AddressLine1Txt>
            <CityNm>MONTE SERENO</CityNm>
            <StateAbbreviationCd>CA</StateAbbreviationCd>
            <ZIPCd>95030</ZIPCd>
          </USAddress>
          <TitleTxt>SECRETARY</TitleTxt>
          <AverageHrsPerWkDevotedToPosRt>2.00</AverageHrsPerWkDevotedToPosRt>
          <CompensationAmt>0</CompensationAmt>
          <EmployeeBenefitProgramAmt>0</EmployeeBenefitProgramAmt>
          <ExpenseAccountOtherAllwncAmt>0</ExpenseAccountOtherAllwncAmt>
        </OfficerDirTrstKeyEmplGrp>
        <OfficerDirTrstKeyEmplGrp>
          <PersonNm>CHRISTOPHER LEE</PersonNm>
          <USAddress>
            <AddressLine1Txt>15997 GRANDVIEW AVENUE</AddressLine1Txt>
            <CityNm>MONTE SERENO</CityNm>
            <StateAbbreviationCd>CA</StateAbbreviationCd>
            <ZIPCd>95030</ZIPCd>
          </USAddress>
          <TitleTxt>CHIEF FINANCIAL OFFICER</TitleTxt>
          <AverageHrsPerWkDevotedToPosRt>2.00</AverageHrsPerWkDevotedToPosRt>
          <CompensationAmt>0</CompensationAmt>
          <EmployeeBenefitProgramAmt>0</EmployeeBenefitProgramAmt>
          <ExpenseAccountOtherAllwncAmt>0</ExpenseAccountOtherAllwncAmt>
        </OfficerDirTrstKeyEmplGrp>
        <OfficerDirTrstKeyEmplGrp>
          <PersonNm>MOURA CT LEE</PersonNm>
          <USAddress>
            <AddressLine1Txt>15997 GRANDVIEW AVENUE</AddressLine1Txt>
            <CityNm>MONTE SERENO</CityNm>
            <StateAbbreviationCd>CA</StateAbbreviationCd>
            <ZIPCd>95030</ZIPCd>
          </USAddress>
          <TitleTxt>DIRECTOR</TitleTxt>
          <AverageHrsPerWkDevotedToPosRt>1.00</AverageHrsPerWkDevotedToPosRt>
          <CompensationAmt>0</CompensationAmt>
          <EmployeeBenefitProgramAmt>0</EmployeeBenefitProgramAmt>
          <ExpenseAccountOtherAllwncAmt>0</ExpenseAccountOtherAllwncAmt>
        </OfficerDirTrstKeyEmplGrp>
        <CompOfHghstPdEmplOrNONETxt>NONE</CompOfHghstPdEmplOrNONETxt>
        <OtherEmployeePaidOver50kCnt>0</OtherEmployeePaidOver50kCnt>
        <CompOfHghstPdCntrctOrNONETxt>NONE</CompOfHghstPdCntrctOrNONETxt>
        <ContractorPaidOver50kCnt>0</ContractorPaidOver50kCnt>
      </OfficerDirTrstKeyEmplInfoGrp>
      <SumOfProgramRelatedInvstGrp>
        <TotalAmt>0</TotalAmt>
      </SumOfProgramRelatedInvstGrp>
      <MinimumInvestmentReturnGrp>
        <AverageMonthlyFMVOfSecAmt>14557</AverageMonthlyFMVOfSecAmt>
        <AverageMonthlyCashBalancesAmt>3887</AverageMonthlyCashBalancesAmt>
        <FMVAllOtherNoncharitableAstAmt>0</FMVAllOtherNoncharitableAstAmt>
        <TotalFMVOfUnusedAssetsAmt>18444</TotalFMVOfUnusedAssetsAmt>
        <ReductionClaimedAmt>0</ReductionClaimedAmt>
        <AcquisitionIndebtednessAmt>0</AcquisitionIndebtednessAmt>
        <AdjustedTotalFMVOfUnusedAstAmt>18444</AdjustedTotalFMVOfUnusedAstAmt>
        <CashDeemedCharitableAmt>277</CashDeemedCharitableAmt>
        <NetVlNoncharitableAssetsAmt>18167</NetVlNoncharitableAssetsAmt>
        <MinimumInvestmentReturnAmt>908</MinimumInvestmentReturnAmt>
      </MinimumInvestmentReturnGrp>
      <DistributableAmountGrp>
        <MinimumInvestmentReturnAmt>908</MinimumInvestmentReturnAmt>
        <TotalTaxAmt>0</TotalTaxAmt>
        <DistributableBeforeAdjAmt>908</DistributableBeforeAdjAmt>
        <RecoveriesQualfiedDistriAmt>0</RecoveriesQualfiedDistriAmt>
        <DistributableBeforeDedAmt>908</DistributableBeforeDedAmt>
        <DeductionFromDistributableAmt>0</DeductionFromDistributableAmt>
        <DistributableAsAdjustedAmt>908</DistributableAsAdjustedAmt>
      </DistributableAmountGrp>
      <QualifyingDistriPartXIIGrp>
        <ExpensesAndContributionsAmt>750</ExpensesAndContributionsAmt>
        <ProgramRelatedInvstTotalAmt>0</ProgramRelatedInvstTotalAmt>
        <QualifyingDistributionsAmt>750</QualifyingDistributionsAmt>
        <PctSect4940eOrgNetInvstIncmAmt>0</PctSect4940eOrgNetInvstIncmAmt>
        <AdjustedQualifyingDistriAmt>750</AdjustedQualifyingDistriAmt>
      </QualifyingDistriPartXIIGrp>
      <UndistributedIncomeGrp>
        <DistributableAsAdjustedAmt>908</DistributableAsAdjustedAmt>
        <UndistributedIncomePYAmt>0</UndistributedIncomePYAmt>
        <TotalForPriorYearsAmt>0</TotalForPriorYearsAmt>
        <ExcessDistributionCyovYr2Amt>18241</ExcessDistributionCyovYr2Amt>
        <ExcessDistributionCyovYr1Amt>29341</ExcessDistributionCyovYr1Amt>
        <TotalExcessDistributionCyovAmt>47582</TotalExcessDistributionCyovAmt>
        <QualifyingDistributionsAmt>750</QualifyingDistributionsAmt>
        <AppliedToYear1Amt>0</AppliedToYear1Amt>
        <AppliedToPriorYearsAmt>0</AppliedToPriorYearsAmt>
        <TreatedAsDistriFromCorpusAmt>0</TreatedAsDistriFromCorpusAmt>
        <AppliedToCurrentYearAmt>750</AppliedToCurrentYearAmt>
        <RemainingDistriFromCorpusAmt>0</RemainingDistriFromCorpusAmt>
        <ExcessDistriCyovAppCYCorpusAmt>158</ExcessDistriCyovAppCYCorpusAmt>
        <ExcessDistributionCyovAppCYAmt>158</ExcessDistributionCyovAppCYAmt>
        <TotalCorpusAmt>47424</TotalCorpusAmt>
        <PriorYearUndistributedIncmAmt>0</PriorYearUndistributedIncmAmt>
        <PriorYearDeficiencyOrTaxAmt>0</PriorYearDeficiencyOrTaxAmt>
        <Taxable1Amt>0</Taxable1Amt>
        <Taxable2Amt>0</Taxable2Amt>
        <UndistributedIncomeCYAmt>0</UndistributedIncomeCYAmt>
        <CorpusDistri170b1EOr4942g3Amt>0</CorpusDistri170b1EOr4942g3Amt>
        <ExcessDistriCyovFromYr5Amt>0</ExcessDistriCyovFromYr5Amt>
        <ExcessDistriCyovToNextYrAmt>47424</ExcessDistriCyovToNextYrAmt>
        <ExcessFromYear2Amt>18083</ExcessFromYear2Amt>
        <ExcessFromYear1Amt>29341</ExcessFromYear1Amt>
      </UndistributedIncomeGrp>
      <SupplementaryInformationGrp>
        <ContributingManagerNm>TSU-WEI FRANK LEE</ContributingManagerNm>
        <OnlyContriToPreselectedInd>X</OnlyContriToPreselectedInd>
        <TotalGrantOrContriPdDurYrAmt>0</TotalGrantOrContriPdDurYrAmt>
        <TotalGrantOrContriApprvFutAmt>0</TotalGrantOrContriApprvFutAmt>
      </SupplementaryInformationGrp>
      <AnalysisIncomeProducingActyGrp>
        <DivAndIntFromSecPartVIIGrp>
          <ExclusionCd>14</ExclusionCd>
          <ExclusionAmt>440</ExclusionAmt>
        </DivAndIntFromSecPartVIIGrp>
        <GainSalesAstOthThanInvntryGrp>
          <ExclusionCd>18</ExclusionCd>
          <ExclusionAmt>1368</ExclusionAmt>
        </GainSalesAstOthThanInvntryGrp>
        <SubtotalsIncmProducingActyGrp>
          <UnrelatedBusinessTaxblIncmAmt>0</UnrelatedBusinessTaxblIncmAmt>
          <ExclusionAmt>1808</ExclusionAmt>
          <RelatedOrExemptFunctionIncmAmt>0</RelatedOrExemptFunctionIncmAmt>
        </SubtotalsIncmProducingActyGrp>
        <TotalIncomeProducingActyAmt>1808</TotalIncomeProducingActyAmt>
      </AnalysisIncomeProducingActyGrp>
      <TrnsfrTransRlnNonchrtblEOGrp>
        <TrnsfrOfCashToNonchrtblEOInd>0</TrnsfrOfCashToNonchrtblEOInd>
        <TrnsfrOtherAssetNonchrtblEOInd>0</TrnsfrOtherAssetNonchrtblEOInd>
        <SalesOrExchangesOfAssetsInd>0</SalesOrExchangesOfAssetsInd>
        <PurchaseOfAssetsNonchrtblEOInd>0</PurchaseOfAssetsNonchrtblEOInd>
        <RentalOfFacilitiesOthAssetsInd>0</RentalOfFacilitiesOthAssetsInd>
        <ReimbursementArrangementsInd>0</ReimbursementArrangementsInd>
        <LoansOrLoanGuaranteesInd>0</LoansOrLoanGuaranteesInd>
        <PerformanceOfServicesEtcInd>0</PerformanceOfServicesEtcInd>
        <SharingOfFacilitiesEtcInd>0</SharingOfFacilitiesEtcInd>
        <RelationshipsNonchrtblEOInd>0</RelationshipsNonchrtblEOInd>
      </TrnsfrTransRlnNonchrtblEOGrp>
    </IRS990PF>
    <AccountingFeesSchedule documentId="RetDoc2002200001">
      <AccountingFeesDetail>
        <CategoryTxt>ACCOUNTING FEES</CategoryTxt>
        <Amt>2850</Amt>
        <NetInvestmentIncomeAmt>2100</NetInvestmentIncomeAmt>
        <DisbursementsCharitablePrpsAmt>750</DisbursementsCharitablePrpsAmt>
      </AccountingFeesDetail>
    </AccountingFeesSchedule>
    <InvestmentsCorpStockSchedule documentId="RetDoc2018900001">
      <InvestmentsCorporateStockGrp>
        <EOYBookValueAmt>49</EOYBookValueAmt>
        <EOYFMVAmt>10550</EOYFMVAmt>
      </InvestmentsCorporateStockGrp>
    </InvestmentsCorpStockSchedule>
    <OtherExpensesSchedule documentId="RetDoc2003200001">
      <OtherExpensesScheduleGrp>
        <Desc>BANK CHARGE</Desc>
        <RevenueAndExpensesPerBooksAmt>450</RevenueAndExpensesPerBooksAmt>
        <NetInvestmentIncomeAmt>450</NetInvestmentIncomeAmt>
        <DisbursementsCharitablePrpsAmt>0</DisbursementsCharitablePrpsAmt>
      </OtherExpensesScheduleGrp>
    </OtherExpensesSchedule>
    <TaxesSchedule documentId="RetDoc2002500001">
      <TaxesDetail>
        <CategoryTxt>TAX AND LICENSES</CategoryTxt>
        <Amt>152</Amt>
        <NetInvestmentIncomeAmt>152</NetInvestmentIncomeAmt>
        <DisbursementsCharitablePrpsAmt>0</DisbursementsCharitablePrpsAmt>
      </TaxesDetail>
    </TaxesSchedule>
  </ReturnData>
</Return>