<?xml version="1.0" encoding="utf-8"?>
<Return xmlns="http://www.irs.gov/efile" xmlns:xsi="http://www.w3.org/2001/XMLSchema-instance" returnVersion="2015v2.1" xsi:schemaLocation="http://www.irs.gov/efile">
  <ReturnHeader binaryAttachmentCnt="0">
    <ReturnTs>2016-09-12T15:01:36-07:00</ReturnTs>
    <TaxPeriodEndDt>2016-04-30</TaxPeriodEndDt>
    <PreparerFirmGrp>
      <PreparerFirmName>
        <BusinessNameLine1Txt>Hosack Specht Muetzel &amp; Wood LLP</BusinessNameLine1Txt>
      </PreparerFirmName>
      <PreparerUSAddress>
        <AddressLine1Txt>2 Penn Center West Suite 326</AddressLine1Txt>
        <CityNm>Pittsburgh</CityNm>
        <StateAbbreviationCd>PA</StateAbbreviationCd>
        <ZIPCd>15276</ZIPCd>
      </PreparerUSAddress>
    </PreparerFirmGrp>
    <ReturnTypeCd>990EZ</ReturnTypeCd>
    <TaxPeriodBeginDt>2015-05-01</TaxPeriodBeginDt>
    <Filer>
      <EIN>251837725</EIN>
      <BusinessName>
        <BusinessNameLine1Txt>Pittsburgh Travel Hockey Association Inc</BusinessNameLine1Txt>
      </BusinessName>
      <BusinessNameControlTxt>PITT</BusinessNameControlTxt>
      <PhoneNum>4122908043</PhoneNum>
      <USAddress>
        <AddressLine1Txt>5412 Lantern Hill Drive Ext</AddressLine1Txt>
        <CityNm>Pittsburgh</CityNm>
        <StateAbbreviationCd>PA</StateAbbreviationCd>
        <ZIPCd>15236</ZIPCd>
      </USAddress>
    </Filer>
    <BusinessOfficerGrp>
      <PersonNm>JOHN ZIVKOVIC CPA</PersonNm>
      <PersonTitleTxt>TREASURER</PersonTitleTxt>
      <PhoneNum>4122908043</PhoneNum>
      <SignatureDt>2015-09-07</SignatureDt>
      <DiscussWithPaidPreparerInd>true</DiscussWithPaidPreparerInd>
    </BusinessOfficerGrp>
    <PreparerPersonGrp>
      <PreparerPersonNm>JOHN ZIVKOVIC CPA</PreparerPersonNm>
      <PhoneNum>4123439200</PhoneNum>
    </PreparerPersonGrp>
    <TaxYr>2015</TaxYr>
    <BuildTS>2017-02-10 21:41:12Z</BuildTS>
  </ReturnHeader>
  <ReturnData documentCnt="3">
    <IRS990EZ documentId="00000001" referenceDocumentName="IRS990ScheduleO ReasonableCauseExplanation TransfersPersonalBenefitsContractsDeclaration">
      <AddressChangeInd>X</AddressChangeInd>
      <MethodOfAccountingAccrualInd>X</MethodOfAccountingAccrualInd>
      <ScheduleBNotRequiredInd>X</ScheduleBNotRequiredInd>
      <WebsiteAddressTxt>N/A</WebsiteAddressTxt>
      <Organization501c3Ind referenceDocumentId="00000002" referenceDocumentName="IRS990ScheduleA">X</Organization501c3Ind>
      <TypeOfOrganizationCorpInd>X</TypeOfOrganizationCorpInd>
      <GrossReceiptsAmt>112</GrossReceiptsAmt>
      <InfoInScheduleOPartIInd>X</InfoInScheduleOPartIInd>
      <ContributionsGiftsGrantsEtcAmt>0</ContributionsGiftsGrantsEtcAmt>
      <ProgramServiceRevenueAmt>0</ProgramServiceRevenueAmt>
      <MembershipDuesAmt>0</MembershipDuesAmt>
      <InvestmentIncomeAmt>112</InvestmentIncomeAmt>
      <CostOrOtherBasisExpenseSaleAmt>0</CostOrOtherBasisExpenseSaleAmt>
      <GainOrLossFromSaleOfAssetsAmt>0</GainOrLossFromSaleOfAssetsAmt>
      <GamingGrossIncomeAmt>0</GamingGrossIncomeAmt>
      <FundraisingGrossIncomeAmt>0</FundraisingGrossIncomeAmt>
      <SpecialEventsDirectExpensesAmt>0</SpecialEventsDirectExpensesAmt>
      <SpecialEventsNetIncomeLossAmt>0</SpecialEventsNetIncomeLossAmt>
      <CostOfGoodsSoldAmt>0</CostOfGoodsSoldAmt>
      <GrossProfitLossSlsOfInvntryAmt>0</GrossProfitLossSlsOfInvntryAmt>
      <TotalRevenueAmt>112</TotalRevenueAmt>
      <GrantsAndSimilarAmountsPaidAmt>14888</GrantsAndSimilarAmountsPaidAmt>
      <FeesAndOtherPymtToIndCntrctAmt>250</FeesAndOtherPymtToIndCntrctAmt>
      <OtherExpensesTotalAmt>150</OtherExpensesTotalAmt>
      <TotalExpensesAmt>15288</TotalExpensesAmt>
      <ExcessOrDeficitForYearAmt>-15176</ExcessOrDeficitForYearAmt>
      <NetAssetsOrFundBalancesBOYAmt>129645</NetAssetsOrFundBalancesBOYAmt>
      <NetAssetsOrFundBalancesEOYAmt>114469</NetAssetsOrFundBalancesEOYAmt>
      <CashSavingsAndInvestmentsGrp>
        <BOYAmt>129645</BOYAmt>
        <EOYAmt>114469</EOYAmt>
      </CashSavingsAndInvestmentsGrp>
      <Form990TotalAssetsGrp>
        <BOYAmt>129645</BOYAmt>
        <EOYAmt>114469</EOYAmt>
      </Form990TotalAssetsGrp>
      <NetAssetsOrFundBalancesGrp>
        <BOYAmt>129645</BOYAmt>
        <EOYAmt>114469</EOYAmt>
      </NetAssetsOrFundBalancesGrp>
      <PrimaryExemptPurposeTxt>Provide youth hockey for players age 10 to 18</PrimaryExemptPurposeTxt>
      <ProgramSrvcAccomplishmentGrp>
        <DescriptionProgramSrvcAccomTxt>Competitive travel ice hockey association for amateur players age 10 to 18 organizied to instill core values to each player</DescriptionProgramSrvcAccomTxt>
        <ProgramServiceExpensesAmt>15288</ProgramServiceExpensesAmt>
      </ProgramSrvcAccomplishmentGrp>
      <TotalProgramServiceExpensesAmt>15288</TotalProgramServiceExpensesAmt>
      <OfficerDirectorTrusteeEmplGrp>
        <PersonNm>CHARLES POTTER</PersonNm>
        <TitleTxt>President</TitleTxt>
        <AverageHrsPerWkDevotedToPosRt>1.00</AverageHrsPerWkDevotedToPosRt>
        <CompensationAmt>0</CompensationAmt>
      </OfficerDirectorTrusteeEmplGrp>
      <OfficerDirectorTrusteeEmplGrp>
        <PersonNm>KATHY HOUSTON</PersonNm>
        <TitleTxt>CFO</TitleTxt>
        <AverageHrsPerWkDevotedToPosRt>1.00</AverageHrsPerWkDevotedToPosRt>
        <CompensationAmt>0</CompensationAmt>
      </OfficerDirectorTrusteeEmplGrp>
      <OfficerDirectorTrusteeEmplGrp>
        <PersonNm>MIKE MAGULICK</PersonNm>
        <TitleTxt>Secretary</TitleTxt>
        <AverageHrsPerWkDevotedToPosRt>1.00</AverageHrsPerWkDevotedToPosRt>
        <CompensationAmt>0</CompensationAmt>
      </OfficerDirectorTrusteeEmplGrp>
      <OfficerDirectorTrusteeEmplGrp>
        <PersonNm>JEFF POTTER</PersonNm>
        <TitleTxt>Director of Hockey Operations</TitleTxt>
        <AverageHrsPerWkDevotedToPosRt>1.00</AverageHrsPerWkDevotedToPosRt>
        <CompensationAmt>0</CompensationAmt>
      </OfficerDirectorTrusteeEmplGrp>
      <OfficerDirectorTrusteeEmplGrp>
        <PersonNm>JOHN ZIVKOVIC</PersonNm>
        <TitleTxt>Treasurer</TitleTxt>
        <AverageHrsPerWkDevotedToPosRt>1.00</AverageHrsPerWkDevotedToPosRt>
        <CompensationAmt>0</CompensationAmt>
      </OfficerDirectorTrusteeEmplGrp>
      <ActivitiesNotPreviouslyRptInd>false</ActivitiesNotPreviouslyRptInd>
      <ChgMadeToOrgnzngDocNotRptInd>false</ChgMadeToOrgnzngDocNotRptInd>
      <OrganizationHadUBIInd>false</OrganizationHadUBIInd>
      <SubjectToProxyTaxInd referenceDocumentName="IRS990ScheduleC">false</SubjectToProxyTaxInd>
      <OrganizationDissolvedEtcInd referenceDocumentName="IRS990ScheduleN BinaryAttachment">false</OrganizationDissolvedEtcInd>
      <Form1120PolFiledInd>false</Form1120PolFiledInd>
      <MadeLoansToFromOfficersInd>false</MadeLoansToFromOfficersInd>
      <EngagedInExcessBenefitTransInd>false</EngagedInExcessBenefitTransInd>
      <ProhibitedTaxShelterTransInd>false</ProhibitedTaxShelterTransInd>
      <BooksInCareOfDetail>
        <PersonNm>JOHN ZIVKOVIC CPA</PersonNm>
        <USAddress>
          <AddressLine1Txt>5412 Lantern Hill Drive Ext</AddressLine1Txt>
          <CityNm>Pittsburgh</CityNm>
          <StateAbbreviationCd>PA</StateAbbreviationCd>
          <ZIPCd>15236</ZIPCd>
        </USAddress>
        <PhoneNum>4122908043</PhoneNum>
      </BooksInCareOfDetail>
      <ForeignFinancialAccountInd>false</ForeignFinancialAccountInd>
      <ForeignOfficeInd>false</ForeignOfficeInd>
      <DonorAdvisedFndsInd>false</DonorAdvisedFndsInd>
      <OperateHospitalInd>false</OperateHospitalInd>
      <TanningServicesProvidedInd>false</TanningServicesProvidedInd>
      <RelatedOrganizationCtrlEntInd>false</RelatedOrganizationCtrlEntInd>
      <TransactionWithControlEntInd>false</TransactionWithControlEntInd>
      <PoliticalCampaignActyInd>false</PoliticalCampaignActyInd>
      <LobbyingActivitiesInd>false</LobbyingActivitiesInd>
      <SchoolOperatingInd>false</SchoolOperatingInd>
      <TrnsfrExmptNonChrtblRltdOrgInd>false</TrnsfrExmptNonChrtblRltdOrgInd>
      <RelatedOrgSect527OrgInd>false</RelatedOrgSect527OrgInd>
      <PartVIOfCompOfHghstPdEmplTxt>NONE</PartVIOfCompOfHghstPdEmplTxt>
      <PartVIHghstPdCntrctProfSrvcTxt>NONE</PartVIHghstPdCntrctProfSrvcTxt>
      <FiledScheduleAInd>false</FiledScheduleAInd>
    </IRS990EZ>
    <IRS990ScheduleA documentId="00000002" softwareId="15000272">
      <PubliclySupportedOrg509a2Ind>X</PubliclySupportedOrg509a2Ind>
      <PublicSupportTotal170Amt>0</PublicSupportTotal170Amt>
      <GrossInvestmentIncome170Grp>
        <TotalAmt>0</TotalAmt>
      </GrossInvestmentIncome170Grp>
      <PublicSupportCY170Pct>0</PublicSupportCY170Pct>
      <GiftsGrantsContrisRcvd509Grp>
        <CurrentTaxYearMinus4YearsAmt>1259</CurrentTaxYearMinus4YearsAmt>
        <TotalAmt>1259</TotalAmt>
      </GiftsGrantsContrisRcvd509Grp>
      <GrossReceiptsAdmissionsGrp>
        <CurrentTaxYearMinus4YearsAmt>523708</CurrentTaxYearMinus4YearsAmt>
        <TotalAmt>523708</TotalAmt>
      </GrossReceiptsAdmissionsGrp>
      <Total509Grp>
        <CurrentTaxYearMinus4YearsAmt>524967</CurrentTaxYearMinus4YearsAmt>
        <TotalAmt>524967</TotalAmt>
      </Total509Grp>
      <AmountsRcvdDsqlfyPersonGrp>
        <CurrentTaxYearMinus4YearsAmt>15400</CurrentTaxYearMinus4YearsAmt>
        <TotalAmt>15400</TotalAmt>
      </AmountsRcvdDsqlfyPersonGrp>
      <SubstAndDsqlfyPrsnsTotGrp>
        <CurrentTaxYearMinus4YearsAmt>15400</CurrentTaxYearMinus4YearsAmt>
        <TotalAmt>15400</TotalAmt>
      </SubstAndDsqlfyPrsnsTotGrp>
      <PublicSupportTotal509Amt>509567</PublicSupportTotal509Amt>
      <GrossInvestmentIncome509Grp>
        <CurrentTaxYearMinus4YearsAmt>573</CurrentTaxYearMinus4YearsAmt>
        <CurrentTaxYearMinus3YearsAmt>292</CurrentTaxYearMinus3YearsAmt>
        <CurrentTaxYearMinus2YearsAmt>198</CurrentTaxYearMinus2YearsAmt>
        <CurrentTaxYearMinus1YearAmt>125</CurrentTaxYearMinus1YearAmt>
        <CurrentTaxYearAmt>112</CurrentTaxYearAmt>
        <TotalAmt>1300</TotalAmt>
      </GrossInvestmentIncome509Grp>
      <InvestmentIncomeAndUBTIGrp>
        <CurrentTaxYearMinus4YearsAmt>573</CurrentTaxYearMinus4YearsAmt>
        <CurrentTaxYearMinus3YearsAmt>292</CurrentTaxYearMinus3YearsAmt>
        <CurrentTaxYearMinus2YearsAmt>198</CurrentTaxYearMinus2YearsAmt>
        <CurrentTaxYearMinus1YearAmt>125</CurrentTaxYearMinus1YearAmt>
        <CurrentTaxYearAmt>112</CurrentTaxYearAmt>
        <TotalAmt>1300</TotalAmt>
      </InvestmentIncomeAndUBTIGrp>
      <TotalSupportCalendarYearGrp>
        <TotalAmt>526267</TotalAmt>
      </TotalSupportCalendarYearGrp>
      <PublicSupportCY509Pct>0.96830</PublicSupportCY509Pct>
      <PublicSupportPY509Pct>0.98240</PublicSupportPY509Pct>
      <InvestmentIncomeCYPct>0.00250</InvestmentIncomeCYPct>
      <InvestmentIncomePYPct>0.00140</InvestmentIncomePYPct>
      <ThirtyThrPctSuprtTestsCY509Ind>X</ThirtyThrPctSuprtTestsCY509Ind>
    </IRS990ScheduleA>
    <IRS990ScheduleO documentId="00000003" softwareId="15000272">
      <SupplementalInformationDetail>
        <FormAndLineReferenceDesc>Form 990EZ, Part I, Line 10</FormAndLineReferenceDesc>
        <ExplanationTxt>TO PROVIDE SCHOLARSHIPS FOR NEEDY PARTICIPANTS; CASH; PITTSBURGH PENGUINS ELITE AMATEUR HOCKEY: 1001</ExplanationTxt>
      </SupplementalInformationDetail>
      <SupplementalInformationDetail>
        <FormAndLineReferenceDesc>Form 990EZ, Part I, Line 10</FormAndLineReferenceDesc>
        <ExplanationTxt>TO PROVIDE SCHOLARSHIPS FOR NEEDY PARTICIPANTS; CASH; ESMARK STARS: 547 CHESTER DRIVE, LOWER BURRELL</ExplanationTxt>
      </SupplementalInformationDetail>
      <SupplementalInformationDetail>
        <FormAndLineReferenceDesc>Form 990EZ, Part I, Line 10</FormAndLineReferenceDesc>
        <ExplanationTxt>TO PROVIDE SCHOLARSHIPS FOR NEEDY PARTICIPANTS; CASH; U 18 SELECTS: 700 CRAIGDELL ROAD, NEW KENSINGT</ExplanationTxt>
      </SupplementalInformationDetail>
      <SupplementalInformationDetail>
        <FormAndLineReferenceDesc>Form 990EZ, Part I, Line 16</FormAndLineReferenceDesc>
        <ExplanationTxt>Miscellaneous Expense 150.</ExplanationTxt>
      </SupplementalInformationDetail>
      <SupplementalInformationDetail>
        <FormAndLineReferenceDesc>Form 990EZ, Part II, Line 24</FormAndLineReferenceDesc>
        <ExplanationTxt>Accounts Receivable</ExplanationTxt>
      </SupplementalInformationDetail>
      <SupplementalInformationDetail>
        <FormAndLineReferenceDesc>Form 990EZ, Part II, Line 24</FormAndLineReferenceDesc>
        <ExplanationTxt>Inventory of Uniforms</ExplanationTxt>
      </SupplementalInformationDetail>
      <SupplementalInformationDetail>
        <FormAndLineReferenceDesc>Form 990EZ, Part II, Line 24</FormAndLineReferenceDesc>
        <ExplanationTxt>Prepaid Expenses</ExplanationTxt>
      </SupplementalInformationDetail>
      <SupplementalInformationDetail>
        <FormAndLineReferenceDesc>Form 990EZ, Part II, Line 26</FormAndLineReferenceDesc>
        <ExplanationTxt>Accounts Payable</ExplanationTxt>
      </SupplementalInformationDetail>
      <SupplementalInformationDetail>
        <FormAndLineReferenceDesc>Form 990EZ, Part II, Line 26</FormAndLineReferenceDesc>
        <ExplanationTxt>Deferred Revenue</ExplanationTxt>
      </SupplementalInformationDetail>
      <SupplementalInformationDetail>
        <FormAndLineReferenceDesc>Form 990, Part IX, Line 24e</FormAndLineReferenceDesc>
        <ExplanationTxt>Pucks</ExplanationTxt>
      </SupplementalInformationDetail>
      <SupplementalInformationDetail>
        <FormAndLineReferenceDesc>Form 990, Part IX, Line 24e</FormAndLineReferenceDesc>
        <ExplanationTxt>Web Page</ExplanationTxt>
      </SupplementalInformationDetail>
      <SupplementalInformationDetail>
        <FormAndLineReferenceDesc>Form 990, Part IX, Line 24e</FormAndLineReferenceDesc>
        <ExplanationTxt>Travel Expense</ExplanationTxt>
      </SupplementalInformationDetail>
      <SupplementalInformationDetail>
        <FormAndLineReferenceDesc>Form 990, Part IX, Line 24e</FormAndLineReferenceDesc>
        <ExplanationTxt>Office Expense</ExplanationTxt>
      </SupplementalInformationDetail>
      <SupplementalInformationDetail>
        <FormAndLineReferenceDesc>Form 990, Part IX, Line 24e</FormAndLineReferenceDesc>
        <ExplanationTxt>Goalie Coach</ExplanationTxt>
      </SupplementalInformationDetail>
      <SupplementalInformationDetail>
        <FormAndLineReferenceDesc>Form 990, Part IX, Line 24e</FormAndLineReferenceDesc>
        <ExplanationTxt>Bookkeeping</ExplanationTxt>
      </SupplementalInformationDetail>
      <SupplementalInformationDetail>
        <FormAndLineReferenceDesc>Form 990, Part IX, Line 24e</FormAndLineReferenceDesc>
        <ExplanationTxt>Refund</ExplanationTxt>
      </SupplementalInformationDetail>
      <SupplementalInformationDetail>
        <FormAndLineReferenceDesc>Form 990, Part IX, Line 24e</FormAndLineReferenceDesc>
        <ExplanationTxt>Miscellaneous</ExplanationTxt>
      </SupplementalInformationDetail>
      <SupplementalInformationDetail>
        <FormAndLineReferenceDesc>Form 990, Part IX, Line 24e</FormAndLineReferenceDesc>
        <ExplanationTxt>Referee's</ExplanationTxt>
      </SupplementalInformationDetail>
      <SupplementalInformationDetail>
        <FormAndLineReferenceDesc>Form 990, Part IX, Line 24e</FormAndLineReferenceDesc>
        <ExplanationTxt>League Fees</ExplanationTxt>
      </SupplementalInformationDetail>
      <SupplementalInformationDetail>
        <FormAndLineReferenceDesc>Form 990, Part IX, Line 24e</FormAndLineReferenceDesc>
        <ExplanationTxt>Tournament Fees</ExplanationTxt>
      </SupplementalInformationDetail>
      <SupplementalInformationDetail>
        <FormAndLineReferenceDesc>Form 990, Part IX, Line 24e</FormAndLineReferenceDesc>
        <ExplanationTxt>Ice Rental Fees</ExplanationTxt>
      </SupplementalInformationDetail>
      <SupplementalInformationDetail>
        <FormAndLineReferenceDesc>Form 990, Part IX, Line 24e</FormAndLineReferenceDesc>
        <ExplanationTxt>Credit Card Commission</ExplanationTxt>
      </SupplementalInformationDetail>
      <SupplementalInformationDetail>
        <FormAndLineReferenceDesc>Form 990, Part IX, Line 24e</FormAndLineReferenceDesc>
        <ExplanationTxt>Decals</ExplanationTxt>
      </SupplementalInformationDetail>
      <SupplementalInformationDetail>
        <FormAndLineReferenceDesc>Form 990, Part IX, Line 24e</FormAndLineReferenceDesc>
        <ExplanationTxt>Printing</ExplanationTxt>
      </SupplementalInformationDetail>
      <SupplementalInformationDetail>
        <FormAndLineReferenceDesc>Form 990, Part IX, Line 24e</FormAndLineReferenceDesc>
        <ExplanationTxt>Jerseys and Socks</ExplanationTxt>
      </SupplementalInformationDetail>
    </IRS990ScheduleO>
  </ReturnData>
</Return>