<?xml version="1.0" encoding="utf-8"?>
<Return xmlns="http://www.irs.gov/efile" xmlns:xsi="http://www.w3.org/2001/XMLSchema-instance" xsi:schemaLocation="http://www.irs.gov/efile" returnVersion="2015v2.1">
  <ReturnHeader binaryAttachmentCnt="0">
    <ReturnTs>2016-09-09T08:41:22-00:00</ReturnTs>
    <TaxPeriodEndDt>2016-03-31</TaxPeriodEndDt>
    <PreparerFirmGrp>
      <PreparerFirmName>
        <BusinessNameLine1Txt>Jusco LLC</BusinessNameLine1Txt>
      </PreparerFirmName>
      <PreparerUSAddress>
        <AddressLine1Txt>4295 Lansmoore Xing</AddressLine1Txt>
        <CityNm>Suwanee</CityNm>
        <StateAbbreviationCd>GA</StateAbbreviationCd>
        <ZIPCd>30024</ZIPCd>
      </PreparerUSAddress>
    </PreparerFirmGrp>
    <ReturnTypeCd>990EZ</ReturnTypeCd>
    <TaxPeriodBeginDt>2015-04-01</TaxPeriodBeginDt>
    <Filer>
      <EIN>271138481</EIN>
      <BusinessName>
        <BusinessNameLine1Txt>Mountain View Band Association Inc</BusinessNameLine1Txt>
      </BusinessName>
      <BusinessNameControlTxt>MOUN</BusinessNameControlTxt>
      <USAddress>
        <AddressLine1Txt>PO Box 490964</AddressLine1Txt>
        <CityNm>Lawrenceville</CityNm>
        <StateAbbreviationCd>GA</StateAbbreviationCd>
        <ZIPCd>30049</ZIPCd>
      </USAddress>
    </Filer>
    <BusinessOfficerGrp>
      <PersonNm>Lisa Gynes</PersonNm>
      <PersonTitleTxt>Treasurer</PersonTitleTxt>
      <SignatureDt>2016-09-09</SignatureDt>
      <DiscussWithPaidPreparerInd>false</DiscussWithPaidPreparerInd>
    </BusinessOfficerGrp>
    <PreparerPersonGrp>
      <PreparerPersonNm>Karen Justice</PreparerPersonNm>
      <PhoneNum>6785415051</PhoneNum>
      <PreparationDt>2016-09-09</PreparationDt>
      <SelfEmployedInd>X</SelfEmployedInd>
    </PreparerPersonGrp>
    <TaxYr>2015</TaxYr>
    <BuildTS>2017-02-10 21:41:12Z</BuildTS>
  </ReturnHeader>
  <ReturnData documentCnt="5">
    <IRS990EZ documentId="990EZ" softwareId="15000290" softwareVersionNum="15.3.0.0">
      <MethodOfAccountingCashInd>X</MethodOfAccountingCashInd>
      <WebsiteAddressTxt>http//www.mtnviewband.com/</WebsiteAddressTxt>
      <Organization501c3Ind referenceDocumentId="990A">X</Organization501c3Ind>
      <TypeOfOrganizationAssocInd>X</TypeOfOrganizationAssocInd>
      <GrossReceiptsAmt>109194</GrossReceiptsAmt>
      <InfoInScheduleOPartIInd>X</InfoInScheduleOPartIInd>
      <ContributionsGiftsGrantsEtcAmt>2133</ContributionsGiftsGrantsEtcAmt>
      <ProgramServiceRevenueAmt>50552</ProgramServiceRevenueAmt>
      <MembershipDuesAmt>56509</MembershipDuesAmt>
      <TotalRevenueAmt>109194</TotalRevenueAmt>
      <FeesAndOtherPymtToIndCntrctAmt>21037</FeesAndOtherPymtToIndCntrctAmt>
      <PrintingPublicationsPostageAmt>22</PrintingPublicationsPostageAmt>
      <OtherExpensesTotalAmt>78744</OtherExpensesTotalAmt>
      <TotalExpensesAmt>99803</TotalExpensesAmt>
      <ExcessOrDeficitForYearAmt>9391</ExcessOrDeficitForYearAmt>
      <NetAssetsOrFundBalancesBOYAmt>10689</NetAssetsOrFundBalancesBOYAmt>
      <NetAssetsOrFundBalancesEOYAmt>20080</NetAssetsOrFundBalancesEOYAmt>
      <CashSavingsAndInvestmentsGrp>
        <BOYAmt>10689</BOYAmt>
        <EOYAmt>20080</EOYAmt>
      </CashSavingsAndInvestmentsGrp>
      <Form990TotalAssetsGrp>
        <BOYAmt>10689</BOYAmt>
        <EOYAmt>20080</EOYAmt>
      </Form990TotalAssetsGrp>
      <NetAssetsOrFundBalancesGrp>
        <BOYAmt>10689</BOYAmt>
        <EOYAmt>20080</EOYAmt>
      </NetAssetsOrFundBalancesGrp>
      <PrimaryExemptPurposeTxt>Support/Facilitate High School Band Activities</PrimaryExemptPurposeTxt>
      <ProgramSrvcAccomplishmentGrp>
        <DescriptionProgramSrvcAccomTxt>Association helps facilitate the music program at Mountain View High School. The marching Band and jazz bands were provided music, supplies, equipment and instruction for various performance activities.</DescriptionProgramSrvcAccomTxt>
        <ProgramServiceExpensesAmt>99803</ProgramServiceExpensesAmt>
      </ProgramSrvcAccomplishmentGrp>
      <TotalProgramServiceExpensesAmt>99803</TotalProgramServiceExpensesAmt>
      <OfficerDirectorTrusteeEmplGrp>
        <PersonNm>Brian Weiner</PersonNm>
        <TitleTxt>President</TitleTxt>
        <AverageHrsPerWkDevotedToPosRt>015.00</AverageHrsPerWkDevotedToPosRt>
        <CompensationAmt>0</CompensationAmt>
      </OfficerDirectorTrusteeEmplGrp>
      <OfficerDirectorTrusteeEmplGrp>
        <PersonNm>Laconia Pete</PersonNm>
        <TitleTxt>CFO</TitleTxt>
        <AverageHrsPerWkDevotedToPosRt>003.00</AverageHrsPerWkDevotedToPosRt>
        <CompensationAmt>0</CompensationAmt>
      </OfficerDirectorTrusteeEmplGrp>
      <OfficerDirectorTrusteeEmplGrp>
        <PersonNm>Dalcita Petteway</PersonNm>
        <TitleTxt>Secretaruy</TitleTxt>
        <AverageHrsPerWkDevotedToPosRt>001.00</AverageHrsPerWkDevotedToPosRt>
        <CompensationAmt>0</CompensationAmt>
      </OfficerDirectorTrusteeEmplGrp>
      <OfficerDirectorTrusteeEmplGrp>
        <PersonNm>Thea Moracci</PersonNm>
        <TitleTxt>Dean of Students</TitleTxt>
        <AverageHrsPerWkDevotedToPosRt>001.00</AverageHrsPerWkDevotedToPosRt>
        <CompensationAmt>0</CompensationAmt>
      </OfficerDirectorTrusteeEmplGrp>
      <OfficerDirectorTrusteeEmplGrp>
        <PersonNm>Doug Carr</PersonNm>
        <TitleTxt>Treasurer</TitleTxt>
        <AverageHrsPerWkDevotedToPosRt>001.00</AverageHrsPerWkDevotedToPosRt>
        <CompensationAmt>0</CompensationAmt>
      </OfficerDirectorTrusteeEmplGrp>
      <ActivitiesNotPreviouslyRptInd>false</ActivitiesNotPreviouslyRptInd>
      <ChgMadeToOrgnzngDocNotRptInd>false</ChgMadeToOrgnzngDocNotRptInd>
      <OrganizationHadUBIInd>false</OrganizationHadUBIInd>
      <SubjectToProxyTaxInd>false</SubjectToProxyTaxInd>
      <OrganizationDissolvedEtcInd>false</OrganizationDissolvedEtcInd>
      <Form1120PolFiledInd>false</Form1120PolFiledInd>
      <MadeLoansToFromOfficersInd>false</MadeLoansToFromOfficersInd>
      <TaxImposedUnderIRC4911Amt>0</TaxImposedUnderIRC4911Amt>
      <TaxImposedUnderIRC4912Amt>0</TaxImposedUnderIRC4912Amt>
      <TaxImposedUnderIRC4955Amt>0</TaxImposedUnderIRC4955Amt>
      <EngagedInExcessBenefitTransInd>false</EngagedInExcessBenefitTransInd>
      <ProhibitedTaxShelterTransInd>false</ProhibitedTaxShelterTransInd>
      <StatesWhereCopyOfReturnIsFldCd>GA</StatesWhereCopyOfReturnIsFldCd>
      <BooksInCareOfDetail>
        <PersonNm>Lisa Gyenes</PersonNm>
        <USAddress>
          <AddressLine1Txt>1750 Millhaven Cove CT</AddressLine1Txt>
          <CityNm>Lawrenceville</CityNm>
          <StateAbbreviationCd>GA</StateAbbreviationCd>
          <ZIPCd>30043</ZIPCd>
        </USAddress>
        <PhoneNum>4049406964</PhoneNum>
      </BooksInCareOfDetail>
      <ForeignFinancialAccountInd>false</ForeignFinancialAccountInd>
      <ForeignOfficeInd>false</ForeignOfficeInd>
      <DonorAdvisedFndsInd>false</DonorAdvisedFndsInd>
      <OperateHospitalInd>false</OperateHospitalInd>
      <TanningServicesProvidedInd>false</TanningServicesProvidedInd>
      <RelatedOrganizationCtrlEntInd>false</RelatedOrganizationCtrlEntInd>
      <TransactionWithControlEntInd>false</TransactionWithControlEntInd>
      <PoliticalCampaignActyInd>false</PoliticalCampaignActyInd>
      <LobbyingActivitiesInd>false</LobbyingActivitiesInd>
      <SchoolOperatingInd>false</SchoolOperatingInd>
      <TrnsfrExmptNonChrtblRltdOrgInd>false</TrnsfrExmptNonChrtblRltdOrgInd>
      <PartVIOfCompOfHghstPdEmplTxt>NONE</PartVIOfCompOfHghstPdEmplTxt>
      <PartVIHghstPdCntrctProfSrvcTxt>NONE</PartVIHghstPdCntrctProfSrvcTxt>
      <FiledScheduleAInd>true</FiledScheduleAInd>
    </IRS990EZ>
    <IRS990ScheduleA documentId="990A" softwareId="15000290" softwareVersionNum="15.3.0.0">
      <PubliclySupportedOrg509a2Ind>X</PubliclySupportedOrg509a2Ind>
      <PublicSupportTotal170Amt>0</PublicSupportTotal170Amt>
      <PublicSupportCY170Pct>0.00000</PublicSupportCY170Pct>
      <GiftsGrantsContrisRcvd509Grp>
        <CurrentTaxYearMinus4YearsAmt>40364</CurrentTaxYearMinus4YearsAmt>
        <CurrentTaxYearMinus3YearsAmt>65038</CurrentTaxYearMinus3YearsAmt>
        <CurrentTaxYearMinus2YearsAmt>95812</CurrentTaxYearMinus2YearsAmt>
        <CurrentTaxYearMinus1YearAmt>119794</CurrentTaxYearMinus1YearAmt>
        <CurrentTaxYearAmt>58642</CurrentTaxYearAmt>
        <TotalAmt>379650</TotalAmt>
      </GiftsGrantsContrisRcvd509Grp>
      <GrossReceiptsAdmissionsGrp>
        <CurrentTaxYearMinus4YearsAmt>57171</CurrentTaxYearMinus4YearsAmt>
        <CurrentTaxYearMinus3YearsAmt>31643</CurrentTaxYearMinus3YearsAmt>
        <CurrentTaxYearMinus2YearsAmt>48286</CurrentTaxYearMinus2YearsAmt>
        <CurrentTaxYearMinus1YearAmt>33375</CurrentTaxYearMinus1YearAmt>
        <CurrentTaxYearAmt>50552</CurrentTaxYearAmt>
        <TotalAmt>221027</TotalAmt>
      </GrossReceiptsAdmissionsGrp>
      <Total509Grp>
        <CurrentTaxYearMinus4YearsAmt>97535</CurrentTaxYearMinus4YearsAmt>
        <CurrentTaxYearMinus3YearsAmt>96681</CurrentTaxYearMinus3YearsAmt>
        <CurrentTaxYearMinus2YearsAmt>144098</CurrentTaxYearMinus2YearsAmt>
        <CurrentTaxYearMinus1YearAmt>153169</CurrentTaxYearMinus1YearAmt>
        <CurrentTaxYearAmt>109194</CurrentTaxYearAmt>
        <TotalAmt>600677</TotalAmt>
      </Total509Grp>
      <PublicSupportTotal509Amt>600677</PublicSupportTotal509Amt>
      <GrossInvestmentIncome509Grp>
        <CurrentTaxYearMinus2YearsAmt>8</CurrentTaxYearMinus2YearsAmt>
        <TotalAmt>8</TotalAmt>
      </GrossInvestmentIncome509Grp>
      <Post1975UBTIGrp>
        <TotalAmt>0</TotalAmt>
      </Post1975UBTIGrp>
      <InvestmentIncomeAndUBTIGrp>
        <CurrentTaxYearMinus2YearsAmt>8</CurrentTaxYearMinus2YearsAmt>
        <TotalAmt>8</TotalAmt>
      </InvestmentIncomeAndUBTIGrp>
      <NetIncomeFromOtherUBIGrp>
        <TotalAmt>0</TotalAmt>
      </NetIncomeFromOtherUBIGrp>
      <OtherIncome509Grp>
        <TotalAmt>0</TotalAmt>
      </OtherIncome509Grp>
      <TotalSupportCalendarYearGrp>
        <CurrentTaxYearMinus4YearsAmt>97535</CurrentTaxYearMinus4YearsAmt>
        <CurrentTaxYearMinus3YearsAmt>96681</CurrentTaxYearMinus3YearsAmt>
        <CurrentTaxYearMinus2YearsAmt>144106</CurrentTaxYearMinus2YearsAmt>
        <CurrentTaxYearMinus1YearAmt>153169</CurrentTaxYearMinus1YearAmt>
        <CurrentTaxYearAmt>109194</CurrentTaxYearAmt>
        <TotalAmt>600685</TotalAmt>
      </TotalSupportCalendarYearGrp>
      <PublicSupportCY509Pct>1.00000</PublicSupportCY509Pct>
      <PublicSupportPY509Pct>1.00000</PublicSupportPY509Pct>
      <InvestmentIncomeCYPct>0.00000</InvestmentIncomeCYPct>
      <ThirtyThrPctSuprtTestsCY509Ind>X</ThirtyThrPctSuprtTestsCY509Ind>
    </IRS990ScheduleA>
    <IRS990ScheduleB documentId="990B" softwareId="15000290" softwareVersionNum="15.3.0.0">
      <ContributorInformationGrp>
        <ContributorNum>RESTRICTED</ContributorNum>
        <ContributorBusinessName>
          <BusinessNameLine1>RESTRICTED</BusinessNameLine1>
        </ContributorBusinessName>
        <ContributorUSAddress>
          <AddressLine1>RESTRICTED</AddressLine1>
          <AddressLine2>RESTRICTED</AddressLine2>
          <City>RESTRICTED</City>
          <State>RESTRICTED</State>
          <ZIPCode>RESTRICTED</ZIPCode>
        </ContributorUSAddress>
        <TotalContributionsAmt>RESTRICTED</TotalContributionsAmt>
      </ContributorInformationGrp>
    </IRS990ScheduleB>
    <IRS990ScheduleO documentId="990O" softwareId="15000290" softwareVersionNum="15.3.0.0">
      <SupplementalInformationDetail>
        <FormAndLineReferenceDesc>Form 990-EZ, Part I, Line 16, Other Expenses</FormAndLineReferenceDesc>
        <ExplanationTxt>Travel 2,190</ExplanationTxt>
      </SupplementalInformationDetail>
      <SupplementalInformationDetail>
        <FormAndLineReferenceDesc>Form 990-EZ, Part I, Line 16, Other Expenses</FormAndLineReferenceDesc>
        <ExplanationTxt>Fundraising 19,226</ExplanationTxt>
      </SupplementalInformationDetail>
      <SupplementalInformationDetail>
        <FormAndLineReferenceDesc>Form 990-EZ, Part I, Line 16, Other Expenses</FormAndLineReferenceDesc>
        <ExplanationTxt>Bank Fees 101</ExplanationTxt>
      </SupplementalInformationDetail>
      <SupplementalInformationDetail>
        <FormAndLineReferenceDesc>Form 990-EZ, Part I, Line 16, Other Expenses</FormAndLineReferenceDesc>
        <ExplanationTxt>Insurance 856</ExplanationTxt>
      </SupplementalInformationDetail>
      <SupplementalInformationDetail>
        <FormAndLineReferenceDesc>Form 990-EZ, Part I, Line 16, Other Expenses</FormAndLineReferenceDesc>
        <ExplanationTxt>Misc 1,592</ExplanationTxt>
      </SupplementalInformationDetail>
      <SupplementalInformationDetail>
        <FormAndLineReferenceDesc>Form 990-EZ, Part I, Line 16, Other Expenses</FormAndLineReferenceDesc>
        <ExplanationTxt>Cadet Guard/Winter Guard 7,585</ExplanationTxt>
      </SupplementalInformationDetail>
      <SupplementalInformationDetail>
        <FormAndLineReferenceDesc>Form 990-EZ, Part I, Line 16, Other Expenses</FormAndLineReferenceDesc>
        <ExplanationTxt>Concert Class 13,498</ExplanationTxt>
      </SupplementalInformationDetail>
      <SupplementalInformationDetail>
        <FormAndLineReferenceDesc>Form 990-EZ, Part I, Line 16, Other Expenses</FormAndLineReferenceDesc>
        <ExplanationTxt>Awards/Reception night 7,536</ExplanationTxt>
      </SupplementalInformationDetail>
      <SupplementalInformationDetail>
        <FormAndLineReferenceDesc>Form 990-EZ, Part I, Line 16, Other Expenses</FormAndLineReferenceDesc>
        <ExplanationTxt>Annual Registration 55</ExplanationTxt>
      </SupplementalInformationDetail>
      <SupplementalInformationDetail>
        <FormAndLineReferenceDesc>Form 990-EZ, Part I, Line 16, Other Expenses</FormAndLineReferenceDesc>
        <ExplanationTxt>Uniform Dry Cleaning 2,078</ExplanationTxt>
      </SupplementalInformationDetail>
      <SupplementalInformationDetail>
        <FormAndLineReferenceDesc>Form 990-EZ, Part I, Line 16, Other Expenses</FormAndLineReferenceDesc>
        <ExplanationTxt>Band Camp 2,463</ExplanationTxt>
      </SupplementalInformationDetail>
      <SupplementalInformationDetail>
        <FormAndLineReferenceDesc>Form 990-EZ, Part I, Line 16, Other Expenses</FormAndLineReferenceDesc>
        <ExplanationTxt>Pep Guard 357</ExplanationTxt>
      </SupplementalInformationDetail>
      <SupplementalInformationDetail>
        <FormAndLineReferenceDesc>Form 990-EZ, Part I, Line 16, Other Expenses</FormAndLineReferenceDesc>
        <ExplanationTxt>Uniforms 9,086</ExplanationTxt>
      </SupplementalInformationDetail>
      <SupplementalInformationDetail>
        <FormAndLineReferenceDesc>Form 990-EZ, Part I, Line 16, Other Expenses</FormAndLineReferenceDesc>
        <ExplanationTxt>Marching Band Equipment Expense 11,416</ExplanationTxt>
      </SupplementalInformationDetail>
      <SupplementalInformationDetail>
        <FormAndLineReferenceDesc>Form 990-EZ, Part I, Line 16, Other Expenses</FormAndLineReferenceDesc>
        <ExplanationTxt>Jazz Band 630</ExplanationTxt>
      </SupplementalInformationDetail>
      <SupplementalInformationDetail>
        <FormAndLineReferenceDesc>Form 990-EZ, Part I, Line 16, Other Expenses</FormAndLineReferenceDesc>
        <ExplanationTxt>Competition/Performance Fees 75</ExplanationTxt>
      </SupplementalInformationDetail>
    </IRS990ScheduleO>
    <CompensationExplanation documentId="990EZ:50" softwareId="15000290" softwareVersionNum="15.3.0.0"></CompensationExplanation>
  </ReturnData>
</Return>