<?xml version="1.0" encoding="utf-8"?>
<Return xmlns="http://www.irs.gov/efile" xmlns:xsi="http://www.w3.org/2001/XMLSchema-instance" xsi:schemaLocation="http://www.irs.gov/efile" returnVersion="2015v2.1">
  <ReturnHeader binaryAttachmentCnt="0">
    <ReturnTs>2016-09-01T17:29:47-05:00</ReturnTs>
    <TaxPeriodEndDt>2015-12-31</TaxPeriodEndDt>
    <PreparerFirmGrp>
      <PreparerFirmEIN>930418710</PreparerFirmEIN>
      <PreparerFirmName>
        <BusinessNameLine1Txt>DELAP LLP</BusinessNameLine1Txt>
      </PreparerFirmName>
      <PreparerUSAddress>
        <AddressLine1Txt>5885 MEADOWS ROAD NO 200</AddressLine1Txt>
        <CityNm>LAKE OSWEGO</CityNm>
        <StateAbbreviationCd>OR</StateAbbreviationCd>
        <ZIPCd>97035</ZIPCd>
      </PreparerUSAddress>
    </PreparerFirmGrp>
    <ReturnTypeCd>990</ReturnTypeCd>
    <TaxPeriodBeginDt>2015-01-01</TaxPeriodBeginDt>
    <Filer>
      <EIN>272865980</EIN>
      <BusinessName>
        <BusinessNameLine1Txt>4WORD</BusinessNameLine1Txt>
      </BusinessName>
      <BusinessNameControlTxt>4WOR</BusinessNameControlTxt>
      <PhoneNum>2146164486</PhoneNum>
      <USAddress>
        <AddressLine1Txt>4516 LOVERS LN NO 205</AddressLine1Txt>
        <CityNm>DALLAS</CityNm>
        <StateAbbreviationCd>TX</StateAbbreviationCd>
        <ZIPCd>75225</ZIPCd>
      </USAddress>
    </Filer>
    <BusinessOfficerGrp>
      <PersonNm>DIANE PADDISON</PersonNm>
      <PersonTitleTxt>PRESIDENT</PersonTitleTxt>
      <PhoneNum>2146164486</PhoneNum>
      <SignatureDt>2016-08-26</SignatureDt>
      <DiscussWithPaidPreparerInd>1</DiscussWithPaidPreparerInd>
    </BusinessOfficerGrp>
    <PreparerPersonGrp>
      <PreparerPersonNm>MARK E EKLUND CPA</PreparerPersonNm>
      <PTIN>P00156145</PTIN>
      <PhoneNum>5036974118</PhoneNum>
      <PreparationDt>2016-08-26</PreparationDt>
    </PreparerPersonGrp>
    <TaxYr>2015</TaxYr>
    <BuildTS>2016-12-15 16:53:06Z</BuildTS>
  </ReturnHeader>
  <ReturnData documentCnt="7">
    <IRS990 documentId="RetDoc1038000001" referenceDocumentId="RetDoc1044400001">
      <PrincipalOfficerNm>DIANE PADDISON</PrincipalOfficerNm>
      <USAddress>
        <AddressLine1Txt>4516 LOVERS LN NO 205</AddressLine1Txt>
        <CityNm>DALLAS</CityNm>
        <StateAbbreviationCd>TX</StateAbbreviationCd>
        <ZIPCd>75225</ZIPCd>
      </USAddress>
      <GrossReceiptsAmt>407946</GrossReceiptsAmt>
      <GroupReturnForAffiliatesInd>0</GroupReturnForAffiliatesInd>
      <Organization501c3Ind>X</Organization501c3Ind>
      <WebsiteAddressTxt>WWW.4WORDWOMEN.ORG</WebsiteAddressTxt>
      <TypeOfOrganizationCorpInd>X</TypeOfOrganizationCorpInd>
      <FormationYr>2011</FormationYr>
      <LegalDomicileStateCd>TX</LegalDomicileStateCd>
      <ActivityOrMissionDesc>4WORD CONNECTS, LEADS, AND SUPPORTS PROFESSIONAL CHRISTIAN WOMEN TO ACHIEVE THEIR GOD-GIVEN POTENTIAL. 4WORD'S MISSION IS TO CREATE COMMUNITY AMONGST CHRISTIAN WOMEN SO THAT HEALTHY RELATIONSHIPS GUIDE THEM IN DECISIONS AROUND "THEIR CALLING" AT WORK AND IN THEIR RELATIONSHIPS.</ActivityOrMissionDesc>
      <VotingMembersGoverningBodyCnt>5</VotingMembersGoverningBodyCnt>
      <VotingMembersIndependentCnt>4</VotingMembersIndependentCnt>
      <TotalEmployeeCnt>1</TotalEmployeeCnt>
      <TotalVolunteersCnt>225</TotalVolunteersCnt>
      <TotalGrossUBIAmt>0</TotalGrossUBIAmt>
      <NetUnrelatedBusTxblIncmAmt>0</NetUnrelatedBusTxblIncmAmt>
      <PYContributionsGrantsAmt>268514</PYContributionsGrantsAmt>
      <CYContributionsGrantsAmt>348807</CYContributionsGrantsAmt>
      <PYProgramServiceRevenueAmt>35116</PYProgramServiceRevenueAmt>
      <CYProgramServiceRevenueAmt>56739</CYProgramServiceRevenueAmt>
      <PYInvestmentIncomeAmt>0</PYInvestmentIncomeAmt>
      <CYInvestmentIncomeAmt>0</CYInvestmentIncomeAmt>
      <PYOtherRevenueAmt>1850</PYOtherRevenueAmt>
      <CYOtherRevenueAmt>-54</CYOtherRevenueAmt>
      <PYTotalRevenueAmt>305480</PYTotalRevenueAmt>
      <CYTotalRevenueAmt>405492</CYTotalRevenueAmt>
      <PYGrantsAndSimilarPaidAmt>0</PYGrantsAndSimilarPaidAmt>
      <CYGrantsAndSimilarPaidAmt>0</CYGrantsAndSimilarPaidAmt>
      <PYBenefitsPaidToMembersAmt>0</PYBenefitsPaidToMembersAmt>
      <CYBenefitsPaidToMembersAmt>0</CYBenefitsPaidToMembersAmt>
      <PYSalariesCompEmpBnftPaidAmt>88970</PYSalariesCompEmpBnftPaidAmt>
      <CYSalariesCompEmpBnftPaidAmt>84185</CYSalariesCompEmpBnftPaidAmt>
      <PYTotalProfFndrsngExpnsAmt>0</PYTotalProfFndrsngExpnsAmt>
      <CYTotalProfFndrsngExpnsAmt>0</CYTotalProfFndrsngExpnsAmt>
      <CYTotalFundraisingExpenseAmt>10394</CYTotalFundraisingExpenseAmt>
      <PYOtherExpensesAmt>333477</PYOtherExpensesAmt>
      <CYOtherExpensesAmt>333617</CYOtherExpensesAmt>
      <PYTotalExpensesAmt>422447</PYTotalExpensesAmt>
      <CYTotalExpensesAmt>417802</CYTotalExpensesAmt>
      <PYRevenuesLessExpensesAmt>-116967</PYRevenuesLessExpensesAmt>
      <CYRevenuesLessExpensesAmt>-12310</CYRevenuesLessExpensesAmt>
      <TotalAssetsBOYAmt>180846</TotalAssetsBOYAmt>
      <TotalAssetsEOYAmt>227468</TotalAssetsEOYAmt>
      <TotalLiabilitiesBOYAmt>21584</TotalLiabilitiesBOYAmt>
      <TotalLiabilitiesEOYAmt>80516</TotalLiabilitiesEOYAmt>
      <NetAssetsOrFundBalancesBOYAmt>159262</NetAssetsOrFundBalancesBOYAmt>
      <NetAssetsOrFundBalancesEOYAmt>146952</NetAssetsOrFundBalancesEOYAmt>
      <InfoInScheduleOPartIIIInd>X</InfoInScheduleOPartIIIInd>
      <MissionDesc>4WORD IS AIMING TO NARROW THE GAP IN RESOURCES FACING EVERY WOMAN SERIOUS ABOUT HER CAREER, RELATIONSHIPS, AND FAITH. WITH THE MANTRA OF WORK, LOVE, PRAY THE ORGANIZATION LEADS TODAY'S PROFESSIONAL WOMEN SEEKING BALANCE, CONNECTS BUSY WORKING WOMEN WITH LOCAL PEERS AND MENTORS, AND SUPPORTS THEIR CORE GROUP WITH VARIOUS RESOURCES.</MissionDesc>
      <SignificantNewProgramSrvcInd>0</SignificantNewProgramSrvcInd>
      <SignificantChangeInd>0</SignificantChangeInd>
      <ExpenseAmt>352101</ExpenseAmt>
      <RevenueAmt>56685</RevenueAmt>
      <Desc>1. DEVELOP ACTIVE ONLINE COMMUNITY - 52,350 CUMULATIVE UNIQUE VISITORS IN 2015 VERSUS A GOAL OF 54,000.2. CREATE LOCAL GROUPS WHICH ENABLE FACE-TO-FACE INTERACTION - 17 4WORD: LOCAL GROUPS/AFFILIATES IN FORMATION BY EOY 2015, WITH 3 NEW LAUCHED VERSUS A GOAL OF 6 LAUNCHED.3. ENCOURAGE PEER TO PEER AND ONE ON ONE MENTORING - 139 PAIRS COMPLETED THE 4WORD: MENTOR PROGRAM TO DATE, EXCELLENT/GOOD RATINGS IN ALL CASES.4. PROVIDED ADDITIONAL THOUGHT LEADERSHIP INCLUDING RESOURCES/CONTENT/PARTNERSHIPS - 4WORD HAD ONE OF THE TOP TEN MOST POPULAR ARTICLES OF 2015 FOR CHRISTIANITY TODAY'S, TODAY'S CHRISTIAN WOMAN, TITLED "4 MYTHS THAT ARE GETTING IN THE WAY OF YOUR CALLING". 5. STRATEGICALLY ADVOCATE FOR OUR AUDIENCE - WESTERN SEMINARY PROVIDED RESOURCES TO PRODUCE 3 VIDEOS DURING THE SPRING OF 2015.6. PROVIDE FUND RAISING FOR A FINANCIALLY HEALTHY ORGANIZATION - OVER $351,000 NEW AND $40,000 OF PRIOR COMMITMENTS RECEIVED IN 2015.</Desc>
      <TotalProgramServiceExpensesAmt>352101</TotalProgramServiceExpensesAmt>
      <DescribedInSection501c3Ind referenceDocumentId="RetDoc1039100001">1</DescribedInSection501c3Ind>
      <ScheduleBRequiredInd referenceDocumentId="RetDoc1234500001">1</ScheduleBRequiredInd>
      <PoliticalCampaignActyInd>0</PoliticalCampaignActyInd>
      <LobbyingActivitiesInd>0</LobbyingActivitiesInd>
      <SubjectToProxyTaxInd>0</SubjectToProxyTaxInd>
      <DonorAdvisedFundInd referenceDocumentId="RetDoc1040000001">0</DonorAdvisedFundInd>
      <ConservationEasementsInd referenceDocumentId="RetDoc1040000001">0</ConservationEasementsInd>
      <CollectionsOfArtInd referenceDocumentId="RetDoc1040000001">0</CollectionsOfArtInd>
      <CreditCounselingInd referenceDocumentId="RetDoc1040000001">0</CreditCounselingInd>
      <TempOrPermanentEndowmentsInd referenceDocumentId="RetDoc1040000001">0</TempOrPermanentEndowmentsInd>
      <ReportLandBuildingEquipmentInd referenceDocumentId="RetDoc1040000001">1</ReportLandBuildingEquipmentInd>
      <ReportInvestmentsOtherSecInd referenceDocumentId="RetDoc1040000001">0</ReportInvestmentsOtherSecInd>
      <ReportProgramRelatedInvstInd referenceDocumentId="RetDoc1040000001">0</ReportProgramRelatedInvstInd>
      <ReportOtherAssetsInd referenceDocumentId="RetDoc1040000001">0</ReportOtherAssetsInd>
      <ReportOtherLiabilitiesInd referenceDocumentId="RetDoc1040000001">0</ReportOtherLiabilitiesInd>
      <IncludeFIN48FootnoteInd referenceDocumentId="RetDoc1040000001">0</IncludeFIN48FootnoteInd>
      <IndependentAuditFinclStmtInd referenceDocumentId="RetDoc1040000001">1</IndependentAuditFinclStmtInd>
      <ConsolidatedAuditFinclStmtInd referenceDocumentId="RetDoc1040000001">0</ConsolidatedAuditFinclStmtInd>
      <SchoolOperatingInd>0</SchoolOperatingInd>
      <ForeignOfficeInd>0</ForeignOfficeInd>
      <ForeignActivitiesInd>0</ForeignActivitiesInd>
      <MoreThan5000KToOrgInd>0</MoreThan5000KToOrgInd>
      <MoreThan5000KToIndividualsInd>0</MoreThan5000KToIndividualsInd>
      <ProfessionalFundraisingInd>0</ProfessionalFundraisingInd>
      <FundraisingActivitiesInd>0</FundraisingActivitiesInd>
      <GamingActivitiesInd>0</GamingActivitiesInd>
      <OperateHospitalInd>0</OperateHospitalInd>
      <GrantsToOrganizationsInd>0</GrantsToOrganizationsInd>
      <GrantsToIndividualsInd>0</GrantsToIndividualsInd>
      <ScheduleJRequiredInd>0</ScheduleJRequiredInd>
      <TaxExemptBondsInd>0</TaxExemptBondsInd>
      <EngagedInExcessBenefitTransInd referenceDocumentId="RetDoc1042800001">0</EngagedInExcessBenefitTransInd>
      <PYExcessBenefitTransInd referenceDocumentId="RetDoc1042800001">0</PYExcessBenefitTransInd>
      <LoanOutstandingInd referenceDocumentId="RetDoc1042800001">0</LoanOutstandingInd>
      <GrantToRelatedPersonInd referenceDocumentId="RetDoc1042800001">0</GrantToRelatedPersonInd>
      <BusinessRlnWithOrgMemInd referenceDocumentId="RetDoc1042800001">1</BusinessRlnWithOrgMemInd>
      <BusinessRlnWithFamMemInd referenceDocumentId="RetDoc1042800001">0</BusinessRlnWithFamMemInd>
      <BusinessRlnWithOfficerEntInd referenceDocumentId="RetDoc1042800001">0</BusinessRlnWithOfficerEntInd>
      <DeductibleNonCashContriInd referenceDocumentId="RetDoc1042900001">1</DeductibleNonCashContriInd>
      <DeductibleArtContributionInd referenceDocumentId="RetDoc1042900001">0</DeductibleArtContributionInd>
      <TerminateOperationsInd>0</TerminateOperationsInd>
      <PartialLiquidationInd>0</PartialLiquidationInd>
      <DisregardedEntityInd>0</DisregardedEntityInd>
      <RelatedEntityInd>0</RelatedEntityInd>
      <RelatedOrganizationCtrlEntInd>0</RelatedOrganizationCtrlEntInd>
      <TrnsfrExmptNonChrtblRltdOrgInd>0</TrnsfrExmptNonChrtblRltdOrgInd>
      <ActivitiesConductedPrtshpInd>0</ActivitiesConductedPrtshpInd>
      <ScheduleORequiredInd>1</ScheduleORequiredInd>
      <IRPDocumentCnt>13</IRPDocumentCnt>
      <IRPDocumentW2GCnt>0</IRPDocumentW2GCnt>
      <BackupWthldComplianceInd>1</BackupWthldComplianceInd>
      <EmployeeCnt>1</EmployeeCnt>
      <EmploymentTaxReturnsFiledInd>1</EmploymentTaxReturnsFiledInd>
      <UnrelatedBusIncmOverLimitInd>0</UnrelatedBusIncmOverLimitInd>
      <ForeignFinancialAccountInd>0</ForeignFinancialAccountInd>
      <ProhibitedTaxShelterTransInd>0</ProhibitedTaxShelterTransInd>
      <TaxablePartyNotificationInd>0</TaxablePartyNotificationInd>
      <NondeductibleContributionsInd>0</NondeductibleContributionsInd>
      <QuidProQuoContributionsInd>0</QuidProQuoContributionsInd>
      <Form8282PropertyDisposedOfInd>0</Form8282PropertyDisposedOfInd>
      <RcvFndsToPayPrsnlBnftCntrctInd>0</RcvFndsToPayPrsnlBnftCntrctInd>
      <PayPremiumsPrsnlBnftCntrctInd>0</PayPremiumsPrsnlBnftCntrctInd>
      <IndoorTanningServicesInd>0</IndoorTanningServicesInd>
      <InfoInScheduleOPartVIInd>X</InfoInScheduleOPartVIInd>
      <GoverningBodyVotingMembersCnt>5</GoverningBodyVotingMembersCnt>
      <IndependentVotingMemberCnt>4</IndependentVotingMemberCnt>
      <FamilyOrBusinessRlnInd>0</FamilyOrBusinessRlnInd>
      <DelegationOfMgmtDutiesInd>1</DelegationOfMgmtDutiesInd>
      <ChangeToOrgDocumentsInd>0</ChangeToOrgDocumentsInd>
      <MaterialDiversionOrMisuseInd>0</MaterialDiversionOrMisuseInd>
      <MembersOrStockholdersInd>0</MembersOrStockholdersInd>
      <ElectionOfBoardMembersInd>0</ElectionOfBoardMembersInd>
      <DecisionsSubjectToApprovaInd>0</DecisionsSubjectToApprovaInd>
      <MinutesOfGoverningBodyInd>1</MinutesOfGoverningBodyInd>
      <MinutesOfCommitteesInd>1</MinutesOfCommitteesInd>
      <OfficerMailingAddressInd>0</OfficerMailingAddressInd>
      <LocalChaptersInd>1</LocalChaptersInd>
      <PoliciesReferenceChaptersInd>1</PoliciesReferenceChaptersInd>
      <Form990ProvidedToGvrnBodyInd>1</Form990ProvidedToGvrnBodyInd>
      <ConflictOfInterestPolicyInd>1</ConflictOfInterestPolicyInd>
      <AnnualDisclosureCoveredPrsnInd>1</AnnualDisclosureCoveredPrsnInd>
      <RegularMonitoringEnfrcInd>1</RegularMonitoringEnfrcInd>
      <WhistleblowerPolicyInd>1</WhistleblowerPolicyInd>
      <DocumentRetentionPolicyInd>1</DocumentRetentionPolicyInd>
      <CompensationProcessCEOInd>0</CompensationProcessCEOInd>
      <CompensationProcessOtherInd>0</CompensationProcessOtherInd>
      <InvestmentInJointVentureInd>0</InvestmentInJointVentureInd>
      <StatesWhereCopyOfReturnIsFldCd>CA</StatesWhereCopyOfReturnIsFldCd>
      <StatesWhereCopyOfReturnIsFldCd>OR</StatesWhereCopyOfReturnIsFldCd>
      <StatesWhereCopyOfReturnIsFldCd>IL</StatesWhereCopyOfReturnIsFldCd>
      <StatesWhereCopyOfReturnIsFldCd>AZ</StatesWhereCopyOfReturnIsFldCd>
      <OtherWebsiteInd>X</OtherWebsiteInd>
      <UponRequestInd>X</UponRequestInd>
      <BooksInCareOfDetail>
        <PersonNm>PASABAN ACCOUNTING SOLUTIONS</PersonNm>
        <PhoneNum>5034676762</PhoneNum>
        <USAddress>
          <AddressLine1Txt>2850 SW CEDAR HILLS BLVD 246</AddressLine1Txt>
          <CityNm>BEAVERTON</CityNm>
          <StateAbbreviationCd>OR</StateAbbreviationCd>
          <ZIPCd>97005</ZIPCd>
        </USAddress>
      </BooksInCareOfDetail>
      <Form990PartVIISectionAGrp>
        <PersonNm>CINDY O'CONNELL</PersonNm>
        <TitleTxt>DIRECTOR</TitleTxt>
        <AverageHoursPerWeekRt>1.00</AverageHoursPerWeekRt>
        <IndividualTrusteeOrDirectorInd>X</IndividualTrusteeOrDirectorInd>
        <ReportableCompFromOrgAmt>2025</ReportableCompFromOrgAmt>
        <ReportableCompFromRltdOrgAmt>0</ReportableCompFromRltdOrgAmt>
        <OtherCompensationAmt>0</OtherCompensationAmt>
      </Form990PartVIISectionAGrp>
      <Form990PartVIISectionAGrp>
        <PersonNm>DIANE PADDISON</PersonNm>
        <TitleTxt>PRESIDENT</TitleTxt>
        <AverageHoursPerWeekRt>60.00</AverageHoursPerWeekRt>
        <IndividualTrusteeOrDirectorInd>X</IndividualTrusteeOrDirectorInd>
        <OfficerInd>X</OfficerInd>
        <ReportableCompFromOrgAmt>0</ReportableCompFromOrgAmt>
        <ReportableCompFromRltdOrgAmt>0</ReportableCompFromRltdOrgAmt>
        <OtherCompensationAmt>0</OtherCompensationAmt>
      </Form990PartVIISectionAGrp>
      <Form990PartVIISectionAGrp>
        <PersonNm>ERIN BOTSFORD</PersonNm>
        <TitleTxt>DIRECTOR</TitleTxt>
        <AverageHoursPerWeekRt>1.00</AverageHoursPerWeekRt>
        <IndividualTrusteeOrDirectorInd>X</IndividualTrusteeOrDirectorInd>
        <ReportableCompFromOrgAmt>0</ReportableCompFromOrgAmt>
        <ReportableCompFromRltdOrgAmt>0</ReportableCompFromRltdOrgAmt>
        <OtherCompensationAmt>0</OtherCompensationAmt>
      </Form990PartVIISectionAGrp>
      <Form990PartVIISectionAGrp>
        <PersonNm>GABRIELLE GREEN</PersonNm>
        <TitleTxt>DIRECTOR</TitleTxt>
        <AverageHoursPerWeekRt>1.00</AverageHoursPerWeekRt>
        <IndividualTrusteeOrDirectorInd>X</IndividualTrusteeOrDirectorInd>
        <ReportableCompFromOrgAmt>0</ReportableCompFromOrgAmt>
        <ReportableCompFromRltdOrgAmt>0</ReportableCompFromRltdOrgAmt>
        <OtherCompensationAmt>0</OtherCompensationAmt>
      </Form990PartVIISectionAGrp>
      <Form990PartVIISectionAGrp>
        <PersonNm>KELLY MCDERMOTT</PersonNm>
        <TitleTxt>DIRECTOR</TitleTxt>
        <AverageHoursPerWeekRt>1.00</AverageHoursPerWeekRt>
        <IndividualTrusteeOrDirectorInd>X</IndividualTrusteeOrDirectorInd>
        <ReportableCompFromOrgAmt>0</ReportableCompFromOrgAmt>
        <ReportableCompFromRltdOrgAmt>0</ReportableCompFromRltdOrgAmt>
        <OtherCompensationAmt>0</OtherCompensationAmt>
      </Form990PartVIISectionAGrp>
      <Form990PartVIISectionAGrp>
        <PersonNm>PAM JOHNSON</PersonNm>
        <TitleTxt>DIRECTOR</TitleTxt>
        <AverageHoursPerWeekRt>1.00</AverageHoursPerWeekRt>
        <IndividualTrusteeOrDirectorInd>X</IndividualTrusteeOrDirectorInd>
        <ReportableCompFromOrgAmt>0</ReportableCompFromOrgAmt>
        <ReportableCompFromRltdOrgAmt>0</ReportableCompFromRltdOrgAmt>
        <OtherCompensationAmt>0</OtherCompensationAmt>
      </Form990PartVIISectionAGrp>
      <Form990PartVIISectionAGrp>
        <PersonNm>RICHELLE CAMPBELL</PersonNm>
        <TitleTxt>SECRETARY</TitleTxt>
        <AverageHoursPerWeekRt>1.00</AverageHoursPerWeekRt>
        <IndividualTrusteeOrDirectorInd>X</IndividualTrusteeOrDirectorInd>
        <OfficerInd>X</OfficerInd>
        <ReportableCompFromOrgAmt>7035</ReportableCompFromOrgAmt>
        <ReportableCompFromRltdOrgAmt>0</ReportableCompFromRltdOrgAmt>
        <OtherCompensationAmt>0</OtherCompensationAmt>
      </Form990PartVIISectionAGrp>
      <TotalReportableCompFromOrgAmt>9060</TotalReportableCompFromOrgAmt>
      <TotReportableCompRltdOrgAmt>0</TotReportableCompRltdOrgAmt>
      <TotalOtherCompensationAmt>0</TotalOtherCompensationAmt>
      <IndivRcvdGreaterThan100KCnt>0</IndivRcvdGreaterThan100KCnt>
      <FormerOfcrEmployeesListedInd>0</FormerOfcrEmployeesListedInd>
      <TotalCompGreaterThan150KInd>0</TotalCompGreaterThan150KInd>
      <CompensationFromOtherSrcsInd>0</CompensationFromOtherSrcsInd>
      <CntrctRcvdGreaterThan100KCnt>0</CntrctRcvdGreaterThan100KCnt>
      <AllOtherContributionsAmt>348807</AllOtherContributionsAmt>
      <NoncashContributionsAmt>30000</NoncashContributionsAmt>
      <TotalContributionsAmt>348807</TotalContributionsAmt>
      <ProgramServiceRevenueGrp>
        <Desc>SERVICE FEES &amp; MEMBERS</Desc>
        <BusinessCd>900099</BusinessCd>
        <TotalRevenueColumnAmt>35519</TotalRevenueColumnAmt>
        <RelatedOrExemptFuncIncomeAmt>35519</RelatedOrExemptFuncIncomeAmt>
      </ProgramServiceRevenueGrp>
      <ProgramServiceRevenueGrp>
        <Desc>MENTORSHIP</Desc>
        <BusinessCd>611600</BusinessCd>
        <TotalRevenueColumnAmt>14399</TotalRevenueColumnAmt>
        <RelatedOrExemptFuncIncomeAmt>14399</RelatedOrExemptFuncIncomeAmt>
      </ProgramServiceRevenueGrp>
      <ProgramServiceRevenueGrp>
        <Desc>SPEAKING &amp; WRITING FEE</Desc>
        <BusinessCd>611600</BusinessCd>
        <TotalRevenueColumnAmt>6821</TotalRevenueColumnAmt>
        <RelatedOrExemptFuncIncomeAmt>6821</RelatedOrExemptFuncIncomeAmt>
      </ProgramServiceRevenueGrp>
      <TotalProgramServiceRevenueAmt>56739</TotalProgramServiceRevenueAmt>
      <GrossSalesOfInventoryAmt>2400</GrossSalesOfInventoryAmt>
      <CostOfGoodsSoldAmt>2454</CostOfGoodsSoldAmt>
      <NetIncomeOrLossGrp>
        <TotalRevenueColumnAmt>-54</TotalRevenueColumnAmt>
        <RelatedOrExemptFuncIncomeAmt>-54</RelatedOrExemptFuncIncomeAmt>
      </NetIncomeOrLossGrp>
      <TotalRevenueGrp>
        <TotalRevenueColumnAmt>405492</TotalRevenueColumnAmt>
        <RelatedOrExemptFuncIncomeAmt>56685</RelatedOrExemptFuncIncomeAmt>
        <UnrelatedBusinessRevenueAmt>0</UnrelatedBusinessRevenueAmt>
        <ExclusionAmt>0</ExclusionAmt>
      </TotalRevenueGrp>
      <OtherSalariesAndWagesGrp>
        <TotalAmt>77600</TotalAmt>
        <ProgramServicesAmt>77600</ProgramServicesAmt>
      </OtherSalariesAndWagesGrp>
      <PayrollTaxesGrp>
        <TotalAmt>6585</TotalAmt>
        <ProgramServicesAmt>6585</ProgramServicesAmt>
      </PayrollTaxesGrp>
      <FeesForServicesLegalGrp>
        <TotalAmt>2314</TotalAmt>
        <ManagementAndGeneralAmt>2314</ManagementAndGeneralAmt>
      </FeesForServicesLegalGrp>
      <FeesForServicesAccountingGrp>
        <TotalAmt>26611</TotalAmt>
        <ManagementAndGeneralAmt>26611</ManagementAndGeneralAmt>
      </FeesForServicesAccountingGrp>
      <FeesForServicesOtherGrp>
        <TotalAmt>1770</TotalAmt>
        <ManagementAndGeneralAmt>270</ManagementAndGeneralAmt>
        <FundraisingAmt>1500</FundraisingAmt>
      </FeesForServicesOtherGrp>
      <AdvertisingGrp>
        <TotalAmt>10161</TotalAmt>
        <ProgramServicesAmt>10131</ProgramServicesAmt>
        <ManagementAndGeneralAmt>21</ManagementAndGeneralAmt>
        <FundraisingAmt>9</FundraisingAmt>
      </AdvertisingGrp>
      <OfficeExpensesGrp>
        <TotalAmt>15394</TotalAmt>
        <ProgramServicesAmt>9349</ProgramServicesAmt>
        <ManagementAndGeneralAmt>3528</ManagementAndGeneralAmt>
        <FundraisingAmt>2517</FundraisingAmt>
      </OfficeExpensesGrp>
      <InformationTechnologyGrp>
        <TotalAmt>216756</TotalAmt>
        <ProgramServicesAmt>216416</ProgramServicesAmt>
        <ManagementAndGeneralAmt>340</ManagementAndGeneralAmt>
      </InformationTechnologyGrp>
      <TravelGrp>
        <TotalAmt>15474</TotalAmt>
        <ProgramServicesAmt>8367</ProgramServicesAmt>
        <ManagementAndGeneralAmt>1538</ManagementAndGeneralAmt>
        <FundraisingAmt>5569</FundraisingAmt>
      </TravelGrp>
      <ConferencesMeetingsGrp>
        <TotalAmt>27509</TotalAmt>
        <ProgramServicesAmt>22247</ProgramServicesAmt>
        <ManagementAndGeneralAmt>4463</ManagementAndGeneralAmt>
        <FundraisingAmt>799</FundraisingAmt>
      </ConferencesMeetingsGrp>
      <DepreciationDepletionGrp>
        <TotalAmt>13320</TotalAmt>
        <ProgramServicesAmt>95</ProgramServicesAmt>
        <ManagementAndGeneralAmt>13225</ManagementAndGeneralAmt>
      </DepreciationDepletionGrp>
      <InsuranceGrp>
        <TotalAmt>3425</TotalAmt>
        <ProgramServicesAmt>428</ProgramServicesAmt>
        <ManagementAndGeneralAmt>2997</ManagementAndGeneralAmt>
      </InsuranceGrp>
      <OtherExpensesGrp>
        <Desc>TAXES</Desc>
        <TotalAmt>883</TotalAmt>
        <ProgramServicesAmt>883</ProgramServicesAmt>
      </OtherExpensesGrp>
      <TotalFunctionalExpensesGrp>
        <TotalAmt>417802</TotalAmt>
        <ProgramServicesAmt>352101</ProgramServicesAmt>
        <ManagementAndGeneralAmt>55307</ManagementAndGeneralAmt>
        <FundraisingAmt>10394</FundraisingAmt>
      </TotalFunctionalExpensesGrp>
      <CashNonInterestBearingGrp>
        <BOYAmt>132870</BOYAmt>
        <EOYAmt>162460</EOYAmt>
      </CashNonInterestBearingGrp>
      <PledgesAndGrantsReceivableGrp>
        <BOYAmt>4154</BOYAmt>
        <EOYAmt>30000</EOYAmt>
      </PledgesAndGrantsReceivableGrp>
      <InventoriesForSaleOrUseGrp>
        <BOYAmt>3839</BOYAmt>
        <EOYAmt>5771</EOYAmt>
      </InventoriesForSaleOrUseGrp>
      <PrepaidExpensesDefrdChargesGrp>
        <BOYAmt>3393</BOYAmt>
        <EOYAmt>5967</EOYAmt>
      </PrepaidExpensesDefrdChargesGrp>
      <LandBldgEquipCostOrOtherBssAmt>950</LandBldgEquipCostOrOtherBssAmt>
      <LandBldgEquipAccumDeprecAmt>396</LandBldgEquipAccumDeprecAmt>
      <LandBldgEquipBasisNetGrp>
        <BOYAmt>744</BOYAmt>
        <EOYAmt>554</EOYAmt>
      </LandBldgEquipBasisNetGrp>
      <IntangibleAssetsGrp>
        <BOYAmt>35846</BOYAmt>
        <EOYAmt>22716</EOYAmt>
      </IntangibleAssetsGrp>
      <TotalAssetsGrp>
        <BOYAmt>180846</BOYAmt>
        <EOYAmt>227468</EOYAmt>
      </TotalAssetsGrp>
      <AccountsPayableAccrExpnssGrp>
        <BOYAmt>12405</BOYAmt>
        <EOYAmt>13322</EOYAmt>
      </AccountsPayableAccrExpnssGrp>
      <DeferredRevenueGrp>
        <BOYAmt>9179</BOYAmt>
        <EOYAmt>67194</EOYAmt>
      </DeferredRevenueGrp>
      <TotalLiabilitiesGrp>
        <BOYAmt>21584</BOYAmt>
        <EOYAmt>80516</EOYAmt>
      </TotalLiabilitiesGrp>
      <OrganizationFollowsSFAS117Ind>X</OrganizationFollowsSFAS117Ind>
      <UnrestrictedNetAssetsGrp>
        <BOYAmt>120919</BOYAmt>
        <EOYAmt>116031</EOYAmt>
      </UnrestrictedNetAssetsGrp>
      <TemporarilyRstrNetAssetsGrp>
        <BOYAmt>38343</BOYAmt>
        <EOYAmt>30921</EOYAmt>
      </TemporarilyRstrNetAssetsGrp>
      <TotalNetAssetsFundBalanceGrp>
        <BOYAmt>159262</BOYAmt>
        <EOYAmt>146952</EOYAmt>
      </TotalNetAssetsFundBalanceGrp>
      <TotLiabNetAssetsFundBalanceGrp>
        <BOYAmt>180846</BOYAmt>
        <EOYAmt>227468</EOYAmt>
      </TotLiabNetAssetsFundBalanceGrp>
      <ReconcilationRevenueExpnssAmt>-12310</ReconcilationRevenueExpnssAmt>
      <OtherChangesInNetAssetsAmt>0</OtherChangesInNetAssetsAmt>
      <MethodOfAccountingAccrualInd>X</MethodOfAccountingAccrualInd>
      <AccountantCompileOrReviewInd>0</AccountantCompileOrReviewInd>
      <FSAuditedInd>1</FSAuditedInd>
      <FSAuditedBasisGrp>
        <SeparateBasisFinclStmtInd>X</SeparateBasisFinclStmtInd>
      </FSAuditedBasisGrp>
      <AuditCommitteeInd>0</AuditCommitteeInd>
      <FederalGrantAuditRequiredInd>0</FederalGrantAuditRequiredInd>
    </IRS990>
    <IRS990ScheduleA documentId="RetDoc1039100001">
      <PubliclySupportedOrg509a2Ind>X</PubliclySupportedOrg509a2Ind>
      <GiftsGrantsContrisRcvd509Grp>
        <CurrentTaxYearMinus4YearsAmt>34184</CurrentTaxYearMinus4YearsAmt>
        <CurrentTaxYearMinus3YearsAmt>100175</CurrentTaxYearMinus3YearsAmt>
        <CurrentTaxYearMinus2YearsAmt>424958</CurrentTaxYearMinus2YearsAmt>
        <CurrentTaxYearMinus1YearAmt>268514</CurrentTaxYearMinus1YearAmt>
        <CurrentTaxYearAmt>349079</CurrentTaxYearAmt>
        <TotalAmt>1176910</TotalAmt>
      </GiftsGrantsContrisRcvd509Grp>
      <GrossReceiptsAdmissionsGrp>
        <CurrentTaxYearMinus4YearsAmt>2731</CurrentTaxYearMinus4YearsAmt>
        <CurrentTaxYearMinus3YearsAmt>14900</CurrentTaxYearMinus3YearsAmt>
        <CurrentTaxYearMinus2YearsAmt>23351</CurrentTaxYearMinus2YearsAmt>
        <CurrentTaxYearMinus1YearAmt>37379</CurrentTaxYearMinus1YearAmt>
        <CurrentTaxYearAmt>58869</CurrentTaxYearAmt>
        <TotalAmt>137230</TotalAmt>
      </GrossReceiptsAdmissionsGrp>
      <Total509Grp>
        <CurrentTaxYearMinus4YearsAmt>36915</CurrentTaxYearMinus4YearsAmt>
        <CurrentTaxYearMinus3YearsAmt>115075</CurrentTaxYearMinus3YearsAmt>
        <CurrentTaxYearMinus2YearsAmt>448309</CurrentTaxYearMinus2YearsAmt>
        <CurrentTaxYearMinus1YearAmt>305893</CurrentTaxYearMinus1YearAmt>
        <CurrentTaxYearAmt>407948</CurrentTaxYearAmt>
        <TotalAmt>1314140</TotalAmt>
      </Total509Grp>
      <AmountsRcvdDsqlfyPersonGrp>
        <CurrentTaxYearMinus4YearsAmt>29500</CurrentTaxYearMinus4YearsAmt>
        <CurrentTaxYearMinus3YearsAmt>81545</CurrentTaxYearMinus3YearsAmt>
        <CurrentTaxYearMinus2YearsAmt>220570</CurrentTaxYearMinus2YearsAmt>
        <CurrentTaxYearMinus1YearAmt>96985</CurrentTaxYearMinus1YearAmt>
        <CurrentTaxYearAmt>148000</CurrentTaxYearAmt>
        <TotalAmt>576600</TotalAmt>
      </AmountsRcvdDsqlfyPersonGrp>
      <SubstantialContributorsAmtGrp>
        <TotalAmt>0</TotalAmt>
      </SubstantialContributorsAmtGrp>
      <SubstAndDsqlfyPrsnsTotGrp>
        <CurrentTaxYearMinus4YearsAmt>29500</CurrentTaxYearMinus4YearsAmt>
        <CurrentTaxYearMinus3YearsAmt>81545</CurrentTaxYearMinus3YearsAmt>
        <CurrentTaxYearMinus2YearsAmt>220570</CurrentTaxYearMinus2YearsAmt>
        <CurrentTaxYearMinus1YearAmt>96985</CurrentTaxYearMinus1YearAmt>
        <CurrentTaxYearAmt>148000</CurrentTaxYearAmt>
        <TotalAmt>576600</TotalAmt>
      </SubstAndDsqlfyPrsnsTotGrp>
      <PublicSupportTotal509Amt>737540</PublicSupportTotal509Amt>
      <TotalSupportCalendarYearGrp>
        <CurrentTaxYearMinus4YearsAmt>36915</CurrentTaxYearMinus4YearsAmt>
        <CurrentTaxYearMinus3YearsAmt>115075</CurrentTaxYearMinus3YearsAmt>
        <CurrentTaxYearMinus2YearsAmt>448309</CurrentTaxYearMinus2YearsAmt>
        <CurrentTaxYearMinus1YearAmt>305893</CurrentTaxYearMinus1YearAmt>
        <CurrentTaxYearAmt>407948</CurrentTaxYearAmt>
        <TotalAmt>1314140</TotalAmt>
      </TotalSupportCalendarYearGrp>
      <PublicSupportCY509Pct>0.56120</PublicSupportCY509Pct>
      <InvestmentIncomeCYPct>0.00000</InvestmentIncomeCYPct>
      <ThirtyThrPctSuprtTestsCY509Ind>X</ThirtyThrPctSuprtTestsCY509Ind>
    </IRS990ScheduleA>
    <IRS990ScheduleB documentId="RetDoc1234500001">
      <ContributorInformationGrp>
        <ContributorNum>RESTRICTED</ContributorNum>
        <ContributorBusinessName>
          <BusinessNameLine1>RESTRICTED</BusinessNameLine1>
        </ContributorBusinessName>
        <ContributorUSAddress>
          <AddressLine1>RESTRICTED</AddressLine1>
          <AddressLine2>RESTRICTED</AddressLine2>
          <City>RESTRICTED</City>
          <State>RESTRICTED</State>
          <ZIPCode>RESTRICTED</ZIPCode>
        </ContributorUSAddress>
        <TotalContributionsAmt>RESTRICTED</TotalContributionsAmt>
      </ContributorInformationGrp>
    </IRS990ScheduleB>
    <IRS990ScheduleD documentId="RetDoc1040000001">
      <EquipmentGrp>
        <OtherCostOrOtherBasisAmt>950</OtherCostOrOtherBasisAmt>
        <DepreciationAmt>396</DepreciationAmt>
        <BookValueAmt>554</BookValueAmt>
      </EquipmentGrp>
      <TotalBookValueLandBuildingsAmt>554</TotalBookValueLandBuildingsAmt>
      <TotalRevEtcAuditedFinclStmtAmt>518992</TotalRevEtcAuditedFinclStmtAmt>
      <DonatedServicesAndUseFcltsAmt>113500</DonatedServicesAndUseFcltsAmt>
      <RevenueNotReportedAmt>113500</RevenueNotReportedAmt>
      <RevenueSubtotalAmt>405492</RevenueSubtotalAmt>
      <RevenueNotReportedFinclStmtAmt>0</RevenueNotReportedFinclStmtAmt>
      <TotalRevenuePerForm990Amt>405492</TotalRevenuePerForm990Amt>
      <TotExpnsEtcAuditedFinclStmtAmt>531302</TotExpnsEtcAuditedFinclStmtAmt>
      <DonatedServicesUseFcltsAmt>113500</DonatedServicesUseFcltsAmt>
      <ExpensesNotReportedAmt>113500</ExpensesNotReportedAmt>
      <ExpensesSubtotalAmt>417802</ExpensesSubtotalAmt>
      <ExpensesNotRptFinclStmtAmt>0</ExpensesNotRptFinclStmtAmt>
      <TotalExpensesPerForm990Amt>417802</TotalExpensesPerForm990Amt>
    </IRS990ScheduleD>
    <IRS990ScheduleL documentId="RetDoc1042800001">
      <BusTrInvolveInterestedPrsnGrp>
        <NameOfInterested>
          <PersonNm>SANDRA CRAWFORD WILLIAMSON</PersonNm>
        </NameOfInterested>
        <RelationshipDescriptionTxt>COO TO THE ORGANIZATION</RelationshipDescriptionTxt>
        <TransactionAmt>85000</TransactionAmt>
        <TransactionDesc>SANDRA OWNS CRAWFORD CONSULTING, INC., A CONSULTING BUSINESS. 4WORD USED THIS CONSULTING BUSINESS THROUGH SEPTEMBER 2015.</TransactionDesc>
        <SharingOfRevenuesInd>0</SharingOfRevenuesInd>
      </BusTrInvolveInterestedPrsnGrp>
    </IRS990ScheduleL>
    <IRS990ScheduleM documentId="RetDoc1042900001">
      <OtherNonCashContriTableGrp>
        <NonCashCheckboxInd>X</NonCashCheckboxInd>
        <Desc>PLEDGE</Desc>
        <ContributionCnt>1</ContributionCnt>
        <NoncashContributionsRptF990Amt>30000</NoncashContributionsRptF990Amt>
        <MethodOfDeterminingRevenuesTxt>ACTUAL PLEDGE AMOUNT</MethodOfDeterminingRevenuesTxt>
      </OtherNonCashContriTableGrp>
      <AnyPropertyThatMustBeHeldInd>0</AnyPropertyThatMustBeHeldInd>
      <ReviewProcessUnusualNCGiftsInd>0</ReviewProcessUnusualNCGiftsInd>
      <ThirdPartiesUsedInd>0</ThirdPartiesUsedInd>
    </IRS990ScheduleM>
    <IRS990ScheduleO documentId="RetDoc1044400001">
      <SupplementalInformationDetail>
        <FormAndLineReferenceDesc>FORM 990, PART VI, SECTION A, LINE 3</FormAndLineReferenceDesc>
        <ExplanationTxt>THE CHIEF OPERATING OFFICER IS PAID BY HER COMPANY CRAWFORD CREATIVE CONSULTING, INC. AMOUNT PAID IN 2015 WAS $85,000.</ExplanationTxt>
      </SupplementalInformationDetail>
      <SupplementalInformationDetail>
        <FormAndLineReferenceDesc>FORM 990, PART VI, SECTION B, LINE 11</FormAndLineReferenceDesc>
        <ExplanationTxt>A COPY OF FORM 990 IS PROVIDED TO THE ORGANIZATION'S GOVERNING BODY FOR REVIEW. THE DRAFT RETURN MUST BE APPROVED BY THE BOARD'S VOTING MEMBERS PRIOR TO FILING.</ExplanationTxt>
      </SupplementalInformationDetail>
      <SupplementalInformationDetail>
        <FormAndLineReferenceDesc>FORM 990, PART VI, SECTION B, LINE 12C</FormAndLineReferenceDesc>
        <ExplanationTxt>THE BOARD OF DIRECTORS ANNUALLY SIGN A STATEMENT INDICATING THAT THEY READ, UNDERSTAND, AND COMPLY WITH THE CONFLICT OF INTEREST POLICY.</ExplanationTxt>
      </SupplementalInformationDetail>
      <SupplementalInformationDetail>
        <FormAndLineReferenceDesc>FORM 990, PART VI, SECTION C, LINE 19</FormAndLineReferenceDesc>
        <ExplanationTxt>THE ORGANIZATION MAKES ITS GOVERNING DOCUMENTS AND FINANCIAL STATEMENTS AVAILABLE TO THE PUBLIC UPON REQUEST.</ExplanationTxt>
      </SupplementalInformationDetail>
    </IRS990ScheduleO>
  </ReturnData>
</Return>